{"docs": [{"text": "kids today , they don't just want to see heartthrob and master thespian freddie prinze jr . loving on the ladies .", "msg_id": "cv643_29282_0", "label": "negative", "toks": [{"form": "kids", "prnt": null, "lemma": null, "tag": null, "rel": null, "children": [], "feats": {}, "snt_id": null}, {"form": "today", "prnt": null, "lemma": null, "tag": null, "rel": null, "children": [], "feats": {}, "snt_id": null}, {"form": ",", "prnt": null, "lemma": null, "tag": null, "rel": null, "children": [], "feats": {}, "snt_id": null}, {"form": "they", "prnt": null, "lemma": null, "tag": null, "rel": null, "children": [], "feats": {}, "snt_id": null}, {"form": "don't", "prnt": null, "lemma": null, "tag": null, "rel": null, "children": [], "feats": {}, "snt_id": null}, {"form": "just", "prnt": null, "lemma": null, "tag": null, "rel": null, "children": [], "feats": {}, "snt_id": null}, {"form": "want", "prnt": null, "lemma": null, "tag": null, "rel": null, "children": [], "feats": {}, "snt_id": null}, {"form": "to", "prnt": null, "lemma": null, "tag": null, "rel": null, "children": [], "feats": {}, "snt_id": null}, {"form": "see", "prnt": null, "lemma": null, "tag": null, "rel": null, "children": [], "feats": {}, "snt_id": null}, {"form": "heartthrob", "prnt": null, "lemma": null, "tag": null, "rel": null, "children": [], "feats": {}, "snt_id": null}, {"form": "and", "prnt": null, "lemma": null, "tag": null, "rel": null, "children": [], "feats": {}, "snt_id": null}, {"form": "master", "prnt": null, "lemma": null, "tag": null, "rel": null, "children": [], "feats": {}, "snt_id": null}, {"form": "thespian", "prnt": null, "lemma": null, "tag": null, "rel": null, "children": [], "feats": {}, "snt_id": null}, {"form": "freddie", "prnt": null, "lemma": null, "tag": null, "rel": null, "children": [], "feats": {}, "snt_id": null}, {"form": "prinze", "prnt": null, "lemma": null, "tag": null, "rel": null, "children": [], "feats": {}, "snt_id": null}, {"form": "jr", "prnt": null, "lemma": null, "tag": null, "rel": null, "children": [], "feats": {}, "snt_id": null}, {"form": ".", "prnt": null, "lemma": null, "tag": null, "rel": null, "children": [], "feats": {}, "snt_id": null}, {"form": "loving", "prnt": null, "lemma": null, "tag": null, "rel": null, "children": [], "feats": {}, "snt_id": null}, {"form": "on", "prnt": null, "lemma": null, "tag": null, "rel": null, "children": [], "feats": {}, "snt_id": null}, {"form": "the", "prnt": null, "lemma": null, "tag": null, "rel": null, "children": [], "feats": {}, "snt_id": null}, {"form": "ladies", "prnt": null, "lemma": null, "tag": null, "rel": null, "children": [], "feats": {}, "snt_id": null}, {"form": ".", "prnt": null, "lemma": null, "tag": null, "rel": null, "children": [], "feats": {}, "snt_id": null}], "edus": [], "rst_trees": {}, "polarity_scores": []}, {"text": "no , they want to see him doing something that takes a little more in the acting department : namely , playing baseball .", "msg_id": "cv643_29282_1", "label": "negative", "toks": [{"form": "no", "prnt": null, "lemma": null, "tag": null, "rel": null, "children": [], "feats": {}, "snt_id": null}, {"form": ",", "prnt": null, "lemma": null, "tag": null, "rel": null, "children": [], "feats": {}, "snt_id": null}, {"form": "they", "prnt": null, "lemma": null, "tag": null, "rel": null, "children": [], "feats": {}, "snt_id": null}, {"form": "want", "prnt": null, "lemma": null, "tag": null, "rel": null, "children": [], "feats": {}, "snt_id": null}, {"form": "to", "prnt": null, "lemma": null, "tag": null, "rel": null, "children": [], "feats": {}, "snt_id": null}, {"form": "see", "prnt": null, "lemma": null, "tag": null, "rel": null, "children": [], "feats": {}, "snt_id": null}, {"form": "him", "prnt": null, "lemma": null, "tag": null, "rel": null, "children": [], "feats": {}, "snt_id": null}, {"form": "doing", "prnt": null, "lemma": null, "tag": null, "rel": null, "children": [], "feats": {}, "snt_id": null}, {"form": "something", "prnt": null, "lemma": null, "tag": null, "rel": null, "children": [], "feats": {}, "snt_id": null}, {"form": "that", "prnt": null, "lemma": null, "tag": null, "rel": null, "children": [], "feats": {}, "snt_id": null}, {"form": "takes", "prnt": null, "lemma": null, "tag": null, "rel": null, "children": [], "feats": {}, "snt_id": null}, {"form": "a", "prnt": null, "lemma": null, "tag": null, "rel": null, "children": [], "feats": {}, "snt_id": null}, {"form": "little", "prnt": null, "lemma": null, "tag": null, "rel": null, "children": [], "feats": {}, "snt_id": null}, {"form": "more", "prnt": null, "lemma": null, "tag": null, "rel": null, "children": [], "feats": {}, "snt_id": null}, {"form": "in", "prnt": null, "lemma": null, "tag": null, "rel": null, "children": [], "feats": {}, "snt_id": null}, {"form": "the", "prnt": null, "lemma": null, "tag": null, "rel": null, "children": [], "feats": {}, "snt_id": null}, {"form": "acting", "prnt": null, "lemma": null, "tag": null, "rel": null, "children": [], "feats": {}, "snt_id": null}, {"form": "department", "prnt": null, "lemma": null, "tag": null, "rel": null, "children": [], "feats": {}, "snt_id": null}, {"form": ":", "prnt": null, "lemma": null, "tag": null, "rel": null, "children": [], "feats": {}, "snt_id": null}, {"form": "namely", "prnt": null, "lemma": null, "tag": null, "rel": null, "children": [], "feats": {}, "snt_id": null}, {"form": ",", "prnt": null, "lemma": null, "tag": null, "rel": null, "children": [], "feats": {}, "snt_id": null}, {"form": "playing", "prnt": null, "lemma": null, "tag": null, "rel": null, "children": [], "feats": {}, "snt_id": null}, {"form": "baseball", "prnt": null, "lemma": null, "tag": null, "rel": null, "children": [], "feats": {}, "snt_id": null}, {"form": ".", "prnt": null, "lemma": null, "tag": null, "rel": null, "children": [], "feats": {}, "snt_id": null}], "edus": [], "rst_trees": {}, "polarity_scores": []}, {"text": "through a series of drippy voiceovers , we are informed that there's no better proving ground for major league baseball than the cape cod summer baseball leagues , where college also-rans and hopeful dropouts go to play in the hopes of attracting big league attention .", "msg_id": "cv643_29282_2", "label": "negative", "toks": [{"form": "through", "prnt": null, "lemma": null, "tag": null, "rel": null, "children": [], "feats": {}, "snt_id": null}, {"form": "a", "prnt": null, "lemma": null, "tag": null, "rel": null, "children": [], "feats": {}, "snt_id": null}, {"form": "series", "prnt": null, "lemma": null, "tag": null, "rel": null, "children": [], "feats": {}, "snt_id": null}, {"form": "of", "prnt": null, "lemma": null, "tag": null, "rel": null, "children": [], "feats": {}, "snt_id": null}, {"form": "drippy", "prnt": null, "lemma": null, "tag": null, "rel": null, "children": [], "feats": {}, "snt_id": null}, {"form": "voiceovers", "prnt": null, "lemma": null, "tag": null, "rel": null, "children": [], "feats": {}, "snt_id": null}, {"form": ",", "prnt": null, "lemma": null, "tag": null, "rel": null, "children": [], "feats": {}, "snt_id": null}, {"form": "we", "prnt": null, "lemma": null, "tag": null, "rel": null, "children": [], "feats": {}, "snt_id": null}, {"form": "are", "prnt": null, "lemma": null, "tag": null, "rel": null, "children": [], "feats": {}, "snt_id": null}, {"form": "informed", "prnt": null, "lemma": null, "tag": null, "rel": null, "children": [], "feats": {}, "snt_id": null}, {"form": "that", "prnt": null, "lemma": null, "tag": null, "rel": null, "children": [], "feats": {}, "snt_id": null}, {"form": "there's", "prnt": null, "lemma": null, "tag": null, "rel": null, "children": [], "feats": {}, "snt_id": null}, {"form": "no", "prnt": null, "lemma": null, "tag": null, "rel": null, "children": [], "feats": {}, "snt_id": null}, {"form": "better", "prnt": null, "lemma": null, "tag": null, "rel": null, "children": [], "feats": {}, "snt_id": null}, {"form": "proving", "prnt": null, "lemma": null, "tag": null, "rel": null, "children": [], "feats": {}, "snt_id": null}, {"form": "ground", "prnt": null, "lemma": null, "tag": null, "rel": null, "children": [], "feats": {}, "snt_id": null}, {"form": "for", "prnt": null, "lemma": null, "tag": null, "rel": null, "children": [], "feats": {}, "snt_id": null}, {"form": "major", "prnt": null, "lemma": null, "tag": null, "rel": null, "children": [], "feats": {}, "snt_id": null}, {"form": "league", "prnt": null, "lemma": null, "tag": null, "rel": null, "children": [], "feats": {}, "snt_id": null}, {"form": "baseball", "prnt": null, "lemma": null, "tag": null, "rel": null, "children": [], "feats": {}, "snt_id": null}, {"form": "than", "prnt": null, "lemma": null, "tag": null, "rel": null, "children": [], "feats": {}, "snt_id": null}, {"form": "the", "prnt": null, "lemma": null, "tag": null, "rel": null, "children": [], "feats": {}, "snt_id": null}, {"form": "cape", "prnt": null, "lemma": null, "tag": null, "rel": null, "children": [], "feats": {}, "snt_id": null}, {"form": "cod", "prnt": null, "lemma": null, "tag": null, "rel": null, "children": [], "feats": {}, "snt_id": null}, {"form": "summer", "prnt": null, "lemma": null, "tag": null, "rel": null, "children": [], "feats": {}, "snt_id": null}, {"form": "baseball", "prnt": null, "lemma": null, "tag": null, "rel": null, "children": [], "feats": {}, "snt_id": null}, {"form": "leagues", "prnt": null, "lemma": null, "tag": null, "rel": null, "children": [], "feats": {}, "snt_id": null}, {"form": ",", "prnt": null, "lemma": null, "tag": null, "rel": null, "children": [], "feats": {}, "snt_id": null}, {"form": "where", "prnt": null, "lemma": null, "tag": null, "rel": null, "children": [], "feats": {}, "snt_id": null}, {"form": "college", "prnt": null, "lemma": null, "tag": null, "rel": null, "children": [], "feats": {}, "snt_id": null}, {"form": "also-rans", "prnt": null, "lemma": null, "tag": null, "rel": null, "children": [], "feats": {}, "snt_id": null}, {"form": "and", "prnt": null, "lemma": null, "tag": null, "rel": null, "children": [], "feats": {}, "snt_id": null}, {"form": "hopeful", "prnt": null, "lemma": null, "tag": null, "rel": null, "children": [], "feats": {}, "snt_id": null}, {"form": "dropouts", "prnt": null, "lemma": null, "tag": null, "rel": null, "children": [], "feats": {}, "snt_id": null}, {"form": "go", "prnt": null, "lemma": null, "tag": null, "rel": null, "children": [], "feats": {}, "snt_id": null}, {"form": "to", "prnt": null, "lemma": null, "tag": null, "rel": null, "children": [], "feats": {}, "snt_id": null}, {"form": "play", "prnt": null, "lemma": null, "tag": null, "rel": null, "children": [], "feats": {}, "snt_id": null}, {"form": "in", "prnt": null, "lemma": null, "tag": null, "rel": null, "children": [], "feats": {}, "snt_id": null}, {"form": "the", "prnt": null, "lemma": null, "tag": null, "rel": null, "children": [], "feats": {}, "snt_id": null}, {"form": "hopes", "prnt": null, "lemma": null, "tag": null, "rel": null, "children": [], "feats": {}, "snt_id": null}, {"form": "of", "prnt": null, "lemma": null, "tag": null, "rel": null, "children": [], "feats": {}, "snt_id": null}, {"form": "attracting", "prnt": null, "lemma": null, "tag": null, "rel": null, "children": [], "feats": {}, "snt_id": null}, {"form": "big", "prnt": null, "lemma": null, "tag": null, "rel": null, "children": [], "feats": {}, "snt_id": null}, {"form": "league", "prnt": null, "lemma": null, "tag": null, "rel": null, "children": [], "feats": {}, "snt_id": null}, {"form": "attention", "prnt": null, "lemma": null, "tag": null, "rel": null, "children": [], "feats": {}, "snt_id": null}, {"form": ".", "prnt": null, "lemma": null, "tag": null, "rel": null, "children": [], "feats": {}, "snt_id": null}], "edus": [], "rst_trees": {}, "polarity_scores": []}, {"text": "our man freddie has landed a spot as a pitcher on the prestigious chatham a's , where he is hoping for his big break .", "msg_id": "cv643_29282_3", "label": "negative", "toks": [{"form": "our", "prnt": null, "lemma": null, "tag": null, "rel": null, "children": [], "feats": {}, "snt_id": null}, {"form": "man", "prnt": null, "lemma": null, "tag": null, "rel": null, "children": [], "feats": {}, "snt_id": null}, {"form": "freddie", "prnt": null, "lemma": null, "tag": null, "rel": null, "children": [], "feats": {}, "snt_id": null}, {"form": "has", "prnt": null, "lemma": null, "tag": null, "rel": null, "children": [], "feats": {}, "snt_id": null}, {"form": "landed", "prnt": null, "lemma": null, "tag": null, "rel": null, "children": [], "feats": {}, "snt_id": null}, {"form": "a", "prnt": null, "lemma": null, "tag": null, "rel": null, "children": [], "feats": {}, "snt_id": null}, {"form": "spot", "prnt": null, "lemma": null, "tag": null, "rel": null, "children": [], "feats": {}, "snt_id": null}, {"form": "as", "prnt": null, "lemma": null, "tag": null, "rel": null, "children": [], "feats": {}, "snt_id": null}, {"form": "a", "prnt": null, "lemma": null, "tag": null, "rel": null, "children": [], "feats": {}, "snt_id": null}, {"form": "pitcher", "prnt": null, "lemma": null, "tag": null, "rel": null, "children": [], "feats": {}, "snt_id": null}, {"form": "on", "prnt": null, "lemma": null, "tag": null, "rel": null, "children": [], "feats": {}, "snt_id": null}, {"form": "the", "prnt": null, "lemma": null, "tag": null, "rel": null, "children": [], "feats": {}, "snt_id": null}, {"form": "prestigious", "prnt": null, "lemma": null, "tag": null, "rel": null, "children": [], "feats": {}, "snt_id": null}, {"form": "chatham", "prnt": null, "lemma": null, "tag": null, "rel": null, "children": [], "feats": {}, "snt_id": null}, {"form": "a's", "prnt": null, "lemma": null, "tag": null, "rel": null, "children": [], "feats": {}, "snt_id": null}, {"form": ",", "prnt": null, "lemma": null, "tag": null, "rel": null, "children": [], "feats": {}, "snt_id": null}, {"form": "where", "prnt": null, "lemma": null, "tag": null, "rel": null, "children": [], "feats": {}, "snt_id": null}, {"form": "he", "prnt": null, "lemma": null, "tag": null, "rel": null, "children": [], "feats": {}, "snt_id": null}, {"form": "is", "prnt": null, "lemma": null, "tag": null, "rel": null, "children": [], "feats": {}, "snt_id": null}, {"form": "hoping", "prnt": null, "lemma": null, "tag": null, "rel": null, "children": [], "feats": {}, "snt_id": null}, {"form": "for", "prnt": null, "lemma": null, "tag": null, "rel": null, "children": [], "feats": {}, "snt_id": null}, {"form": "his", "prnt": null, "lemma": null, "tag": null, "rel": null, "children": [], "feats": {}, "snt_id": null}, {"form": "big", "prnt": null, "lemma": null, "tag": null, "rel": null, "children": [], "feats": {}, "snt_id": null}, {"form": "break", "prnt": null, "lemma": null, "tag": null, "rel": null, "children": [], "feats": {}, "snt_id": null}, {"form": ".", "prnt": null, "lemma": null, "tag": null, "rel": null, "children": [], "feats": {}, "snt_id": null}], "edus": [], "rst_trees": {}, "polarity_scores": []}, {"text": "it's only after he is given ample time to show off his abs and scamper about in a woman's thong ( don't ask ) that we learn what the real story of summer catch will be : that prinze is a poor townie named ryan dunne , struggling to make a name for himself ; that neither his father ( fred ward ) nor brother ( jason gedrick ) pulled themselves out of their blue collar jobs and resent anyone who tries ; and that the local beauty tenley -- tenley !", "msg_id": "cv643_29282_4", "label": "negative", "toks": [{"form": "it's", "prnt": null, "lemma": null, "tag": null, "rel": null, "children": [], "feats": {}, "snt_id": null}, {"form": "only", "prnt": null, "lemma": null, "tag": null, "rel": null, "children": [], "feats": {}, "snt_id": null}, {"form": "after", "prnt": null, "lemma": null, "tag": null, "rel": null, "children": [], "feats": {}, "snt_id": null}, {"form": "he", "prnt": null, "lemma": null, "tag": null, "rel": null, "children": [], "feats": {}, "snt_id": null}, {"form": "is", "prnt": null, "lemma": null, "tag": null, "rel": null, "children": [], "feats": {}, "snt_id": null}, {"form": "given", "prnt": null, "lemma": null, "tag": null, "rel": null, "children": [], "feats": {}, "snt_id": null}, {"form": "ample", "prnt": null, "lemma": null, "tag": null, "rel": null, "children": [], "feats": {}, "snt_id": null}, {"form": "time", "prnt": null, "lemma": null, "tag": null, "rel": null, "children": [], "feats": {}, "snt_id": null}, {"form": "to", "prnt": null, "lemma": null, "tag": null, "rel": null, "children": [], "feats": {}, "snt_id": null}, {"form": "show", "prnt": null, "lemma": null, "tag": null, "rel": null, "children": [], "feats": {}, "snt_id": null}, {"form": "off", "prnt": null, "lemma": null, "tag": null, "rel": null, "children": [], "feats": {}, "snt_id": null}, {"form": "his", "prnt": null, "lemma": null, "tag": null, "rel": null, "children": [], "feats": {}, "snt_id": null}, {"form": "abs", "prnt": null, "lemma": null, "tag": null, "rel": null, "children": [], "feats": {}, "snt_id": null}, {"form": "and", "prnt": null, "lemma": null, "tag": null, "rel": null, "children": [], "feats": {}, "snt_id": null}, {"form": "scamper", "prnt": null, "lemma": null, "tag": null, "rel": null, "children": [], "feats": {}, "snt_id": null}, {"form": "about", "prnt": null, "lemma": null, "tag": null, "rel": null, "children": [], "feats": {}, "snt_id": null}, {"form": "in", "prnt": null, "lemma": null, "tag": null, "rel": null, "children": [], "feats": {}, "snt_id": null}, {"form": "a", "prnt": null, "lemma": null, "tag": null, "rel": null, "children": [], "feats": {}, "snt_id": null}, {"form": "woman's", "prnt": null, "lemma": null, "tag": null, "rel": null, "children": [], "feats": {}, "snt_id": null}, {"form": "thong", "prnt": null, "lemma": null, "tag": null, "rel": null, "children": [], "feats": {}, "snt_id": null}, {"form": "(", "prnt": null, "lemma": null, "tag": null, "rel": null, "children": [], "feats": {}, "snt_id": null}, {"form": "don't", "prnt": null, "lemma": null, "tag": null, "rel": null, "children": [], "feats": {}, "snt_id": null}, {"form": "ask", "prnt": null, "lemma": null, "tag": null, "rel": null, "children": [], "feats": {}, "snt_id": null}, {"form": ")", "prnt": null, "lemma": null, "tag": null, "rel": null, "children": [], "feats": {}, "snt_id": null}, {"form": "that", "prnt": null, "lemma": null, "tag": null, "rel": null, "children": [], "feats": {}, "snt_id": null}, {"form": "we", "prnt": null, "lemma": null, "tag": null, "rel": null, "children": [], "feats": {}, "snt_id": null}, {"form": "learn", "prnt": null, "lemma": null, "tag": null, "rel": null, "children": [], "feats": {}, "snt_id": null}, {"form": "what", "prnt": null, "lemma": null, "tag": null, "rel": null, "children": [], "feats": {}, "snt_id": null}, {"form": "the", "prnt": null, "lemma": null, "tag": null, "rel": null, "children": [], "feats": {}, "snt_id": null}, {"form": "real", "prnt": null, "lemma": null, "tag": null, "rel": null, "children": [], "feats": {}, "snt_id": null}, {"form": "story", "prnt": null, "lemma": null, "tag": null, "rel": null, "children": [], "feats": {}, "snt_id": null}, {"form": "of", "prnt": null, "lemma": null, "tag": null, "rel": null, "children": [], "feats": {}, "snt_id": null}, {"form": "summer", "prnt": null, "lemma": null, "tag": null, "rel": null, "children": [], "feats": {}, "snt_id": null}, {"form": "catch", "prnt": null, "lemma": null, "tag": null, "rel": null, "children": [], "feats": {}, "snt_id": null}, {"form": "will", "prnt": null, "lemma": null, "tag": null, "rel": null, "children": [], "feats": {}, "snt_id": null}, {"form": "be", "prnt": null, "lemma": null, "tag": null, "rel": null, "children": [], "feats": {}, "snt_id": null}, {"form": ":", "prnt": null, "lemma": null, "tag": null, "rel": null, "children": [], "feats": {}, "snt_id": null}, {"form": "that", "prnt": null, "lemma": null, "tag": null, "rel": null, "children": [], "feats": {}, "snt_id": null}, {"form": "prinze", "prnt": null, "lemma": null, "tag": null, "rel": null, "children": [], "feats": {}, "snt_id": null}, {"form": "is", "prnt": null, "lemma": null, "tag": null, "rel": null, "children": [], "feats": {}, "snt_id": null}, {"form": "a", "prnt": null, "lemma": null, "tag": null, "rel": null, "children": [], "feats": {}, "snt_id": null}, {"form": "poor", "prnt": null, "lemma": null, "tag": null, "rel": null, "children": [], "feats": {}, "snt_id": null}, {"form": "townie", "prnt": null, "lemma": null, "tag": null, "rel": null, "children": [], "feats": {}, "snt_id": null}, {"form": "named", "prnt": null, "lemma": null, "tag": null, "rel": null, "children": [], "feats": {}, "snt_id": null}, {"form": "ryan", "prnt": null, "lemma": null, "tag": null, "rel": null, "children": [], "feats": {}, "snt_id": null}, {"form": "dunne", "prnt": null, "lemma": null, "tag": null, "rel": null, "children": [], "feats": {}, "snt_id": null}, {"form": ",", "prnt": null, "lemma": null, "tag": null, "rel": null, "children": [], "feats": {}, "snt_id": null}, {"form": "struggling", "prnt": null, "lemma": null, "tag": null, "rel": null, "children": [], "feats": {}, "snt_id": null}, {"form": "to", "prnt": null, "lemma": null, "tag": null, "rel": null, "children": [], "feats": {}, "snt_id": null}, {"form": "make", "prnt": null, "lemma": null, "tag": null, "rel": null, "children": [], "feats": {}, "snt_id": null}, {"form": "a", "prnt": null, "lemma": null, "tag": null, "rel": null, "children": [], "feats": {}, "snt_id": null}, {"form": "name", "prnt": null, "lemma": null, "tag": null, "rel": null, "children": [], "feats": {}, "snt_id": null}, {"form": "for", "prnt": null, "lemma": null, "tag": null, "rel": null, "children": [], "feats": {}, "snt_id": null}, {"form": "himself", "prnt": null, "lemma": null, "tag": null, "rel": null, "children": [], "feats": {}, "snt_id": null}, {"form": ";", "prnt": null, "lemma": null, "tag": null, "rel": null, "children": [], "feats": {}, "snt_id": null}, {"form": "that", "prnt": null, "lemma": null, "tag": null, "rel": null, "children": [], "feats": {}, "snt_id": null}, {"form": "neither", "prnt": null, "lemma": null, "tag": null, "rel": null, "children": [], "feats": {}, "snt_id": null}, {"form": "his", "prnt": null, "lemma": null, "tag": null, "rel": null, "children": [], "feats": {}, "snt_id": null}, {"form": "father", "prnt": null, "lemma": null, "tag": null, "rel": null, "children": [], "feats": {}, "snt_id": null}, {"form": "(", "prnt": null, "lemma": null, "tag": null, "rel": null, "children": [], "feats": {}, "snt_id": null}, {"form": "fred", "prnt": null, "lemma": null, "tag": null, "rel": null, "children": [], "feats": {}, "snt_id": null}, {"form": "ward", "prnt": null, "lemma": null, "tag": null, "rel": null, "children": [], "feats": {}, "snt_id": null}, {"form": ")", "prnt": null, "lemma": null, "tag": null, "rel": null, "children": [], "feats": {}, "snt_id": null}, {"form": "nor", "prnt": null, "lemma": null, "tag": null, "rel": null, "children": [], "feats": {}, "snt_id": null}, {"form": "brother", "prnt": null, "lemma": null, "tag": null, "rel": null, "children": [], "feats": {}, "snt_id": null}, {"form": "(", "prnt": null, "lemma": null, "tag": null, "rel": null, "children": [], "feats": {}, "snt_id": null}, {"form": "jason", "prnt": null, "lemma": null, "tag": null, "rel": null, "children": [], "feats": {}, "snt_id": null}, {"form": "gedrick", "prnt": null, "lemma": null, "tag": null, "rel": null, "children": [], "feats": {}, "snt_id": null}, {"form": ")", "prnt": null, "lemma": null, "tag": null, "rel": null, "children": [], "feats": {}, "snt_id": null}, {"form": "pulled", "prnt": null, "lemma": null, "tag": null, "rel": null, "children": [], "feats": {}, "snt_id": null}, {"form": "themselves", "prnt": null, "lemma": null, "tag": null, "rel": null, "children": [], "feats": {}, "snt_id": null}, {"form": "out", "prnt": null, "lemma": null, "tag": null, "rel": null, "children": [], "feats": {}, "snt_id": null}, {"form": "of", "prnt": null, "lemma": null, "tag": null, "rel": null, "children": [], "feats": {}, "snt_id": null}, {"form": "their", "prnt": null, "lemma": null, "tag": null, "rel": null, "children": [], "feats": {}, "snt_id": null}, {"form": "blue", "prnt": null, "lemma": null, "tag": null, "rel": null, "children": [], "feats": {}, "snt_id": null}, {"form": "collar", "prnt": null, "lemma": null, "tag": null, "rel": null, "children": [], "feats": {}, "snt_id": null}, {"form": "jobs", "prnt": null, "lemma": null, "tag": null, "rel": null, "children": [], "feats": {}, "snt_id": null}, {"form": "and", "prnt": null, "lemma": null, "tag": null, "rel": null, "children": [], "feats": {}, "snt_id": null}, {"form": "resent", "prnt": null, "lemma": null, "tag": null, "rel": null, "children": [], "feats": {}, "snt_id": null}, {"form": "anyone", "prnt": null, "lemma": null, "tag": null, "rel": null, "children": [], "feats": {}, "snt_id": null}, {"form": "who", "prnt": null, "lemma": null, "tag": null, "rel": null, "children": [], "feats": {}, "snt_id": null}, {"form": "tries", "prnt": null, "lemma": null, "tag": null, "rel": null, "children": [], "feats": {}, "snt_id": null}, {"form": ";", "prnt": null, "lemma": null, "tag": null, "rel": null, "children": [], "feats": {}, "snt_id": null}, {"form": "and", "prnt": null, "lemma": null, "tag": null, "rel": null, "children": [], "feats": {}, "snt_id": null}, {"form": "that", "prnt": null, "lemma": null, "tag": null, "rel": null, "children": [], "feats": {}, "snt_id": null}, {"form": "the", "prnt": null, "lemma": null, "tag": null, "rel": null, "children": [], "feats": {}, "snt_id": null}, {"form": "local", "prnt": null, "lemma": null, "tag": null, "rel": null, "children": [], "feats": {}, "snt_id": null}, {"form": "beauty", "prnt": null, "lemma": null, "tag": null, "rel": null, "children": [], "feats": {}, "snt_id": null}, {"form": "tenley", "prnt": null, "lemma": null, "tag": null, "rel": null, "children": [], "feats": {}, "snt_id": null}, {"form": "--", "prnt": null, "lemma": null, "tag": null, "rel": null, "children": [], "feats": {}, "snt_id": null}, {"form": "tenley", "prnt": null, "lemma": null, "tag": null, "rel": null, "children": [], "feats": {}, "snt_id": null}, {"form": "!", "prnt": null, "lemma": null, "tag": null, "rel": null, "children": [], "feats": {}, "snt_id": null}], "edus": [], "rst_trees": {}, "polarity_scores": []}, {"text": "( jessica biel ) -- is so far out of his league that he probably shouldn't even bother . . .", "msg_id": "cv643_29282_5", "label": "negative", "toks": [{"form": "(", "prnt": null, "lemma": null, "tag": null, "rel": null, "children": [], "feats": {}, "snt_id": null}, {"form": "jessica", "prnt": null, "lemma": null, "tag": null, "rel": null, "children": [], "feats": {}, "snt_id": null}, {"form": "biel", "prnt": null, "lemma": null, "tag": null, "rel": null, "children": [], "feats": {}, "snt_id": null}, {"form": ")", "prnt": null, "lemma": null, "tag": null, "rel": null, "children": [], "feats": {}, "snt_id": null}, {"form": "--", "prnt": null, "lemma": null, "tag": null, "rel": null, "children": [], "feats": {}, "snt_id": null}, {"form": "is", "prnt": null, "lemma": null, "tag": null, "rel": null, "children": [], "feats": {}, "snt_id": null}, {"form": "so", "prnt": null, "lemma": null, "tag": null, "rel": null, "children": [], "feats": {}, "snt_id": null}, {"form": "far", "prnt": null, "lemma": null, "tag": null, "rel": null, "children": [], "feats": {}, "snt_id": null}, {"form": "out", "prnt": null, "lemma": null, "tag": null, "rel": null, "children": [], "feats": {}, "snt_id": null}, {"form": "of", "prnt": null, "lemma": null, "tag": null, "rel": null, "children": [], "feats": {}, "snt_id": null}, {"form": "his", "prnt": null, "lemma": null, "tag": null, "rel": null, "children": [], "feats": {}, "snt_id": null}, {"form": "league", "prnt": null, "lemma": null, "tag": null, "rel": null, "children": [], "feats": {}, "snt_id": null}, {"form": "that", "prnt": null, "lemma": null, "tag": null, "rel": null, "children": [], "feats": {}, "snt_id": null}, {"form": "he", "prnt": null, "lemma": null, "tag": null, "rel": null, "children": [], "feats": {}, "snt_id": null}, {"form": "probably", "prnt": null, "lemma": null, "tag": null, "rel": null, "children": [], "feats": {}, "snt_id": null}, {"form": "shouldn't", "prnt": null, "lemma": null, "tag": null, "rel": null, "children": [], "feats": {}, "snt_id": null}, {"form": "even", "prnt": null, "lemma": null, "tag": null, "rel": null, "children": [], "feats": {}, "snt_id": null}, {"form": "bother", "prnt": null, "lemma": null, "tag": null, "rel": null, "children": [], "feats": {}, "snt_id": null}, {"form": ".", "prnt": null, "lemma": null, "tag": null, "rel": null, "children": [], "feats": {}, "snt_id": null}, {"form": ".", "prnt": null, "lemma": null, "tag": null, "rel": null, "children": [], "feats": {}, "snt_id": null}, {"form": ".", "prnt": null, "lemma": null, "tag": null, "rel": null, "children": [], "feats": {}, "snt_id": null}], "edus": [], "rst_trees": {}, "polarity_scores": []}, {"text": "but of course he makes a play for her .", "msg_id": "cv643_29282_6", "label": "negative", "toks": [{"form": "but", "prnt": null, "lemma": null, "tag": null, "rel": null, "children": [], "feats": {}, "snt_id": null}, {"form": "of", "prnt": null, "lemma": null, "tag": null, "rel": null, "children": [], "feats": {}, "snt_id": null}, {"form": "course", "prnt": null, "lemma": null, "tag": null, "rel": null, "children": [], "feats": {}, "snt_id": null}, {"form": "he", "prnt": null, "lemma": null, "tag": null, "rel": null, "children": [], "feats": {}, "snt_id": null}, {"form": "makes", "prnt": null, "lemma": null, "tag": null, "rel": null, "children": [], "feats": {}, "snt_id": null}, {"form": "a", "prnt": null, "lemma": null, "tag": null, "rel": null, "children": [], "feats": {}, "snt_id": null}, {"form": "play", "prnt": null, "lemma": null, "tag": null, "rel": null, "children": [], "feats": {}, "snt_id": null}, {"form": "for", "prnt": null, "lemma": null, "tag": null, "rel": null, "children": [], "feats": {}, "snt_id": null}, {"form": "her", "prnt": null, "lemma": null, "tag": null, "rel": null, "children": [], "feats": {}, "snt_id": null}, {"form": ".", "prnt": null, "lemma": null, "tag": null, "rel": null, "children": [], "feats": {}, "snt_id": null}], "edus": [], "rst_trees": {}, "polarity_scores": []}, {"text": "summer catch also makes an abortive stab at another half a dozen subplots -- the jealousy of fellow townie and brazen slut dee dee ( brittany murphy ) , the alienation felt by ryan's non-baseball playing best friend ( gabriel mann ) , or the fat chick fetish of fellow player miles ( marc blucas ) .", "msg_id": "cv643_29282_7", "label": "negative", "toks": [{"form": "summer", "prnt": null, "lemma": null, "tag": null, "rel": null, "children": [], "feats": {}, "snt_id": null}, {"form": "catch", "prnt": null, "lemma": null, "tag": null, "rel": null, "children": [], "feats": {}, "snt_id": null}, {"form": "also", "prnt": null, "lemma": null, "tag": null, "rel": null, "children": [], "feats": {}, "snt_id": null}, {"form": "makes", "prnt": null, "lemma": null, "tag": null, "rel": null, "children": [], "feats": {}, "snt_id": null}, {"form": "an", "prnt": null, "lemma": null, "tag": null, "rel": null, "children": [], "feats": {}, "snt_id": null}, {"form": "abortive", "prnt": null, "lemma": null, "tag": null, "rel": null, "children": [], "feats": {}, "snt_id": null}, {"form": "stab", "prnt": null, "lemma": null, "tag": null, "rel": null, "children": [], "feats": {}, "snt_id": null}, {"form": "at", "prnt": null, "lemma": null, "tag": null, "rel": null, "children": [], "feats": {}, "snt_id": null}, {"form": "another", "prnt": null, "lemma": null, "tag": null, "rel": null, "children": [], "feats": {}, "snt_id": null}, {"form": "half", "prnt": null, "lemma": null, "tag": null, "rel": null, "children": [], "feats": {}, "snt_id": null}, {"form": "a", "prnt": null, "lemma": null, "tag": null, "rel": null, "children": [], "feats": {}, "snt_id": null}, {"form": "dozen", "prnt": null, "lemma": null, "tag": null, "rel": null, "children": [], "feats": {}, "snt_id": null}, {"form": "subplots", "prnt": null, "lemma": null, "tag": null, "rel": null, "children": [], "feats": {}, "snt_id": null}, {"form": "--", "prnt": null, "lemma": null, "tag": null, "rel": null, "children": [], "feats": {}, "snt_id": null}, {"form": "the", "prnt": null, "lemma": null, "tag": null, "rel": null, "children": [], "feats": {}, "snt_id": null}, {"form": "jealousy", "prnt": null, "lemma": null, "tag": null, "rel": null, "children": [], "feats": {}, "snt_id": null}, {"form": "of", "prnt": null, "lemma": null, "tag": null, "rel": null, "children": [], "feats": {}, "snt_id": null}, {"form": "fellow", "prnt": null, "lemma": null, "tag": null, "rel": null, "children": [], "feats": {}, "snt_id": null}, {"form": "townie", "prnt": null, "lemma": null, "tag": null, "rel": null, "children": [], "feats": {}, "snt_id": null}, {"form": "and", "prnt": null, "lemma": null, "tag": null, "rel": null, "children": [], "feats": {}, "snt_id": null}, {"form": "brazen", "prnt": null, "lemma": null, "tag": null, "rel": null, "children": [], "feats": {}, "snt_id": null}, {"form": "slut", "prnt": null, "lemma": null, "tag": null, "rel": null, "children": [], "feats": {}, "snt_id": null}, {"form": "dee", "prnt": null, "lemma": null, "tag": null, "rel": null, "children": [], "feats": {}, "snt_id": null}, {"form": "dee", "prnt": null, "lemma": null, "tag": null, "rel": null, "children": [], "feats": {}, "snt_id": null}, {"form": "(", "prnt": null, "lemma": null, "tag": null, "rel": null, "children": [], "feats": {}, "snt_id": null}, {"form": "brittany", "prnt": null, "lemma": null, "tag": null, "rel": null, "children": [], "feats": {}, "snt_id": null}, {"form": "murphy", "prnt": null, "lemma": null, "tag": null, "rel": null, "children": [], "feats": {}, "snt_id": null}, {"form": ")", "prnt": null, "lemma": null, "tag": null, "rel": null, "children": [], "feats": {}, "snt_id": null}, {"form": ",", "prnt": null, "lemma": null, "tag": null, "rel": null, "children": [], "feats": {}, "snt_id": null}, {"form": "the", "prnt": null, "lemma": null, "tag": null, "rel": null, "children": [], "feats": {}, "snt_id": null}, {"form": "alienation", "prnt": null, "lemma": null, "tag": null, "rel": null, "children": [], "feats": {}, "snt_id": null}, {"form": "felt", "prnt": null, "lemma": null, "tag": null, "rel": null, "children": [], "feats": {}, "snt_id": null}, {"form": "by", "prnt": null, "lemma": null, "tag": null, "rel": null, "children": [], "feats": {}, "snt_id": null}, {"form": "ryan's", "prnt": null, "lemma": null, "tag": null, "rel": null, "children": [], "feats": {}, "snt_id": null}, {"form": "non-baseball", "prnt": null, "lemma": null, "tag": null, "rel": null, "children": [], "feats": {}, "snt_id": null}, {"form": "playing", "prnt": null, "lemma": null, "tag": null, "rel": null, "children": [], "feats": {}, "snt_id": null}, {"form": "best", "prnt": null, "lemma": null, "tag": null, "rel": null, "children": [], "feats": {}, "snt_id": null}, {"form": "friend", "prnt": null, "lemma": null, "tag": null, "rel": null, "children": [], "feats": {}, "snt_id": null}, {"form": "(", "prnt": null, "lemma": null, "tag": null, "rel": null, "children": [], "feats": {}, "snt_id": null}, {"form": "gabriel", "prnt": null, "lemma": null, "tag": null, "rel": null, "children": [], "feats": {}, "snt_id": null}, {"form": "mann", "prnt": null, "lemma": null, "tag": null, "rel": null, "children": [], "feats": {}, "snt_id": null}, {"form": ")", "prnt": null, "lemma": null, "tag": null, "rel": null, "children": [], "feats": {}, "snt_id": null}, {"form": ",", "prnt": null, "lemma": null, "tag": null, "rel": null, "children": [], "feats": {}, "snt_id": null}, {"form": "or", "prnt": null, "lemma": null, "tag": null, "rel": null, "children": [], "feats": {}, "snt_id": null}, {"form": "the", "prnt": null, "lemma": null, "tag": null, "rel": null, "children": [], "feats": {}, "snt_id": null}, {"form": "fat", "prnt": null, "lemma": null, "tag": null, "rel": null, "children": [], "feats": {}, "snt_id": null}, {"form": "chick", "prnt": null, "lemma": null, "tag": null, "rel": null, "children": [], "feats": {}, "snt_id": null}, {"form": "fetish", "prnt": null, "lemma": null, "tag": null, "rel": null, "children": [], "feats": {}, "snt_id": null}, {"form": "of", "prnt": null, "lemma": null, "tag": null, "rel": null, "children": [], "feats": {}, "snt_id": null}, {"form": "fellow", "prnt": null, "lemma": null, "tag": null, "rel": null, "children": [], "feats": {}, "snt_id": null}, {"form": "player", "prnt": null, "lemma": null, "tag": null, "rel": null, "children": [], "feats": {}, "snt_id": null}, {"form": "miles", "prnt": null, "lemma": null, "tag": null, "rel": null, "children": [], "feats": {}, "snt_id": null}, {"form": "(", "prnt": null, "lemma": null, "tag": null, "rel": null, "children": [], "feats": {}, "snt_id": null}, {"form": "marc", "prnt": null, "lemma": null, "tag": null, "rel": null, "children": [], "feats": {}, "snt_id": null}, {"form": "blucas", "prnt": null, "lemma": null, "tag": null, "rel": null, "children": [], "feats": {}, "snt_id": null}, {"form": ")", "prnt": null, "lemma": null, "tag": null, "rel": null, "children": [], "feats": {}, "snt_id": null}, {"form": ".", "prnt": null, "lemma": null, "tag": null, "rel": null, "children": [], "feats": {}, "snt_id": null}], "edus": [], "rst_trees": {}, "polarity_scores": []}, {"text": "worst of these is a ludicrous bit involving that '70s show's wilmer valderrama and beverly d'angelo , both of whom appear in the film simply to provide a nutty mrs . robinson-like substory and to remind you of how much better done that was in bull durham .", "msg_id": "cv643_29282_8", "label": "negative", "toks": [{"form": "worst", "prnt": null, "lemma": null, "tag": null, "rel": null, "children": [], "feats": {}, "snt_id": null}, {"form": "of", "prnt": null, "lemma": null, "tag": null, "rel": null, "children": [], "feats": {}, "snt_id": null}, {"form": "these", "prnt": null, "lemma": null, "tag": null, "rel": null, "children": [], "feats": {}, "snt_id": null}, {"form": "is", "prnt": null, "lemma": null, "tag": null, "rel": null, "children": [], "feats": {}, "snt_id": null}, {"form": "a", "prnt": null, "lemma": null, "tag": null, "rel": null, "children": [], "feats": {}, "snt_id": null}, {"form": "ludicrous", "prnt": null, "lemma": null, "tag": null, "rel": null, "children": [], "feats": {}, "snt_id": null}, {"form": "bit", "prnt": null, "lemma": null, "tag": null, "rel": null, "children": [], "feats": {}, "snt_id": null}, {"form": "involving", "prnt": null, "lemma": null, "tag": null, "rel": null, "children": [], "feats": {}, "snt_id": null}, {"form": "that", "prnt": null, "lemma": null, "tag": null, "rel": null, "children": [], "feats": {}, "snt_id": null}, {"form": "'70s", "prnt": null, "lemma": null, "tag": null, "rel": null, "children": [], "feats": {}, "snt_id": null}, {"form": "show's", "prnt": null, "lemma": null, "tag": null, "rel": null, "children": [], "feats": {}, "snt_id": null}, {"form": "wilmer", "prnt": null, "lemma": null, "tag": null, "rel": null, "children": [], "feats": {}, "snt_id": null}, {"form": "valderrama", "prnt": null, "lemma": null, "tag": null, "rel": null, "children": [], "feats": {}, "snt_id": null}, {"form": "and", "prnt": null, "lemma": null, "tag": null, "rel": null, "children": [], "feats": {}, "snt_id": null}, {"form": "beverly", "prnt": null, "lemma": null, "tag": null, "rel": null, "children": [], "feats": {}, "snt_id": null}, {"form": "d'angelo", "prnt": null, "lemma": null, "tag": null, "rel": null, "children": [], "feats": {}, "snt_id": null}, {"form": ",", "prnt": null, "lemma": null, "tag": null, "rel": null, "children": [], "feats": {}, "snt_id": null}, {"form": "both", "prnt": null, "lemma": null, "tag": null, "rel": null, "children": [], "feats": {}, "snt_id": null}, {"form": "of", "prnt": null, "lemma": null, "tag": null, "rel": null, "children": [], "feats": {}, "snt_id": null}, {"form": "whom", "prnt": null, "lemma": null, "tag": null, "rel": null, "children": [], "feats": {}, "snt_id": null}, {"form": "appear", "prnt": null, "lemma": null, "tag": null, "rel": null, "children": [], "feats": {}, "snt_id": null}, {"form": "in", "prnt": null, "lemma": null, "tag": null, "rel": null, "children": [], "feats": {}, "snt_id": null}, {"form": "the", "prnt": null, "lemma": null, "tag": null, "rel": null, "children": [], "feats": {}, "snt_id": null}, {"form": "film", "prnt": null, "lemma": null, "tag": null, "rel": null, "children": [], "feats": {}, "snt_id": null}, {"form": "simply", "prnt": null, "lemma": null, "tag": null, "rel": null, "children": [], "feats": {}, "snt_id": null}, {"form": "to", "prnt": null, "lemma": null, "tag": null, "rel": null, "children": [], "feats": {}, "snt_id": null}, {"form": "provide", "prnt": null, "lemma": null, "tag": null, "rel": null, "children": [], "feats": {}, "snt_id": null}, {"form": "a", "prnt": null, "lemma": null, "tag": null, "rel": null, "children": [], "feats": {}, "snt_id": null}, {"form": "nutty", "prnt": null, "lemma": null, "tag": null, "rel": null, "children": [], "feats": {}, "snt_id": null}, {"form": "mrs", "prnt": null, "lemma": null, "tag": null, "rel": null, "children": [], "feats": {}, "snt_id": null}, {"form": ".", "prnt": null, "lemma": null, "tag": null, "rel": null, "children": [], "feats": {}, "snt_id": null}, {"form": "robinson-like", "prnt": null, "lemma": null, "tag": null, "rel": null, "children": [], "feats": {}, "snt_id": null}, {"form": "substory", "prnt": null, "lemma": null, "tag": null, "rel": null, "children": [], "feats": {}, "snt_id": null}, {"form": "and", "prnt": null, "lemma": null, "tag": null, "rel": null, "children": [], "feats": {}, "snt_id": null}, {"form": "to", "prnt": null, "lemma": null, "tag": null, "rel": null, "children": [], "feats": {}, "snt_id": null}, {"form": "remind", "prnt": null, "lemma": null, "tag": null, "rel": null, "children": [], "feats": {}, "snt_id": null}, {"form": "you", "prnt": null, "lemma": null, "tag": null, "rel": null, "children": [], "feats": {}, "snt_id": null}, {"form": "of", "prnt": null, "lemma": null, "tag": null, "rel": null, "children": [], "feats": {}, "snt_id": null}, {"form": "how", "prnt": null, "lemma": null, "tag": null, "rel": null, "children": [], "feats": {}, "snt_id": null}, {"form": "much", "prnt": null, "lemma": null, "tag": null, "rel": null, "children": [], "feats": {}, "snt_id": null}, {"form": "better", "prnt": null, "lemma": null, "tag": null, "rel": null, "children": [], "feats": {}, "snt_id": null}, {"form": "done", "prnt": null, "lemma": null, "tag": null, "rel": null, "children": [], "feats": {}, "snt_id": null}, {"form": "that", "prnt": null, "lemma": null, "tag": null, "rel": null, "children": [], "feats": {}, "snt_id": null}, {"form": "was", "prnt": null, "lemma": null, "tag": null, "rel": null, "children": [], "feats": {}, "snt_id": null}, {"form": "in", "prnt": null, "lemma": null, "tag": null, "rel": null, "children": [], "feats": {}, "snt_id": null}, {"form": "bull", "prnt": null, "lemma": null, "tag": null, "rel": null, "children": [], "feats": {}, "snt_id": null}, {"form": "durham", "prnt": null, "lemma": null, "tag": null, "rel": null, "children": [], "feats": {}, "snt_id": null}, {"form": ".", "prnt": null, "lemma": null, "tag": null, "rel": null, "children": [], "feats": {}, "snt_id": null}], "edus": [], "rst_trees": {}, "polarity_scores": []}, {"text": "in fact , virtually all of summer catch feels like it's been done better somewhere else .", "msg_id": "cv643_29282_9", "label": "negative", "toks": [{"form": "in", "prnt": null, "lemma": null, "tag": null, "rel": null, "children": [], "feats": {}, "snt_id": null}, {"form": "fact", "prnt": null, "lemma": null, "tag": null, "rel": null, "children": [], "feats": {}, "snt_id": null}, {"form": ",", "prnt": null, "lemma": null, "tag": null, "rel": null, "children": [], "feats": {}, "snt_id": null}, {"form": "virtually", "prnt": null, "lemma": null, "tag": null, "rel": null, "children": [], "feats": {}, "snt_id": null}, {"form": "all", "prnt": null, "lemma": null, "tag": null, "rel": null, "children": [], "feats": {}, "snt_id": null}, {"form": "of", "prnt": null, "lemma": null, "tag": null, "rel": null, "children": [], "feats": {}, "snt_id": null}, {"form": "summer", "prnt": null, "lemma": null, "tag": null, "rel": null, "children": [], "feats": {}, "snt_id": null}, {"form": "catch", "prnt": null, "lemma": null, "tag": null, "rel": null, "children": [], "feats": {}, "snt_id": null}, {"form": "feels", "prnt": null, "lemma": null, "tag": null, "rel": null, "children": [], "feats": {}, "snt_id": null}, {"form": "like", "prnt": null, "lemma": null, "tag": null, "rel": null, "children": [], "feats": {}, "snt_id": null}, {"form": "it's", "prnt": null, "lemma": null, "tag": null, "rel": null, "children": [], "feats": {}, "snt_id": null}, {"form": "been", "prnt": null, "lemma": null, "tag": null, "rel": null, "children": [], "feats": {}, "snt_id": null}, {"form": "done", "prnt": null, "lemma": null, "tag": null, "rel": null, "children": [], "feats": {}, "snt_id": null}, {"form": "better", "prnt": null, "lemma": null, "tag": null, "rel": null, "children": [], "feats": {}, "snt_id": null}, {"form": "somewhere", "prnt": null, "lemma": null, "tag": null, "rel": null, "children": [], "feats": {}, "snt_id": null}, {"form": "else", "prnt": null, "lemma": null, "tag": null, "rel": null, "children": [], "feats": {}, "snt_id": null}, {"form": ".", "prnt": null, "lemma": null, "tag": null, "rel": null, "children": [], "feats": {}, "snt_id": null}], "edus": [], "rst_trees": {}, "polarity_scores": []}, {"text": "for starters , the film has a major question of identity .", "msg_id": "cv643_29282_10", "label": "negative", "toks": [{"form": "for", "prnt": null, "lemma": null, "tag": null, "rel": null, "children": [], "feats": {}, "snt_id": null}, {"form": "starters", "prnt": null, "lemma": null, "tag": null, "rel": null, "children": [], "feats": {}, "snt_id": null}, {"form": ",", "prnt": null, "lemma": null, "tag": null, "rel": null, "children": [], "feats": {}, "snt_id": null}, {"form": "the", "prnt": null, "lemma": null, "tag": null, "rel": null, "children": [], "feats": {}, "snt_id": null}, {"form": "film", "prnt": null, "lemma": null, "tag": null, "rel": null, "children": [], "feats": {}, "snt_id": null}, {"form": "has", "prnt": null, "lemma": null, "tag": null, "rel": null, "children": [], "feats": {}, "snt_id": null}, {"form": "a", "prnt": null, "lemma": null, "tag": null, "rel": null, "children": [], "feats": {}, "snt_id": null}, {"form": "major", "prnt": null, "lemma": null, "tag": null, "rel": null, "children": [], "feats": {}, "snt_id": null}, {"form": "question", "prnt": null, "lemma": null, "tag": null, "rel": null, "children": [], "feats": {}, "snt_id": null}, {"form": "of", "prnt": null, "lemma": null, "tag": null, "rel": null, "children": [], "feats": {}, "snt_id": null}, {"form": "identity", "prnt": null, "lemma": null, "tag": null, "rel": null, "children": [], "feats": {}, "snt_id": null}, {"form": ".", "prnt": null, "lemma": null, "tag": null, "rel": null, "children": [], "feats": {}, "snt_id": null}], "edus": [], "rst_trees": {}, "polarity_scores": []}, {"text": "it's definitely not a sports movie , and it fails pretty miserably at being a romance .", "msg_id": "cv643_29282_11", "label": "negative", "toks": [{"form": "it's", "prnt": null, "lemma": null, "tag": null, "rel": null, "children": [], "feats": {}, "snt_id": null}, {"form": "definitely", "prnt": null, "lemma": null, "tag": null, "rel": null, "children": [], "feats": {}, "snt_id": null}, {"form": "not", "prnt": null, "lemma": null, "tag": null, "rel": null, "children": [], "feats": {}, "snt_id": null}, {"form": "a", "prnt": null, "lemma": null, "tag": null, "rel": null, "children": [], "feats": {}, "snt_id": null}, {"form": "sports", "prnt": null, "lemma": null, "tag": null, "rel": null, "children": [], "feats": {}, "snt_id": null}, {"form": "movie", "prnt": null, "lemma": null, "tag": null, "rel": null, "children": [], "feats": {}, "snt_id": null}, {"form": ",", "prnt": null, "lemma": null, "tag": null, "rel": null, "children": [], "feats": {}, "snt_id": null}, {"form": "and", "prnt": null, "lemma": null, "tag": null, "rel": null, "children": [], "feats": {}, "snt_id": null}, {"form": "it", "prnt": null, "lemma": null, "tag": null, "rel": null, "children": [], "feats": {}, "snt_id": null}, {"form": "fails", "prnt": null, "lemma": null, "tag": null, "rel": null, "children": [], "feats": {}, "snt_id": null}, {"form": "pretty", "prnt": null, "lemma": null, "tag": null, "rel": null, "children": [], "feats": {}, "snt_id": null}, {"form": "miserably", "prnt": null, "lemma": null, "tag": null, "rel": null, "children": [], "feats": {}, "snt_id": null}, {"form": "at", "prnt": null, "lemma": null, "tag": null, "rel": null, "children": [], "feats": {}, "snt_id": null}, {"form": "being", "prnt": null, "lemma": null, "tag": null, "rel": null, "children": [], "feats": {}, "snt_id": null}, {"form": "a", "prnt": null, "lemma": null, "tag": null, "rel": null, "children": [], "feats": {}, "snt_id": null}, {"form": "romance", "prnt": null, "lemma": null, "tag": null, "rel": null, "children": [], "feats": {}, "snt_id": null}, {"form": ".", "prnt": null, "lemma": null, "tag": null, "rel": null, "children": [], "feats": {}, "snt_id": null}], "edus": [], "rst_trees": {}, "polarity_scores": []}, {"text": "the worst part is the amateurish script ( co-written by an arli$$ writing alumnus and a guy that starred in leprechaun 3 ) , chock-full of phony emotion .", "msg_id": "cv643_29282_12", "label": "negative", "toks": [{"form": "the", "prnt": null, "lemma": null, "tag": null, "rel": null, "children": [], "feats": {}, "snt_id": null}, {"form": "worst", "prnt": null, "lemma": null, "tag": null, "rel": null, "children": [], "feats": {}, "snt_id": null}, {"form": "part", "prnt": null, "lemma": null, "tag": null, "rel": null, "children": [], "feats": {}, "snt_id": null}, {"form": "is", "prnt": null, "lemma": null, "tag": null, "rel": null, "children": [], "feats": {}, "snt_id": null}, {"form": "the", "prnt": null, "lemma": null, "tag": null, "rel": null, "children": [], "feats": {}, "snt_id": null}, {"form": "amateurish", "prnt": null, "lemma": null, "tag": null, "rel": null, "children": [], "feats": {}, "snt_id": null}, {"form": "script", "prnt": null, "lemma": null, "tag": null, "rel": null, "children": [], "feats": {}, "snt_id": null}, {"form": "(", "prnt": null, "lemma": null, "tag": null, "rel": null, "children": [], "feats": {}, "snt_id": null}, {"form": "co-written", "prnt": null, "lemma": null, "tag": null, "rel": null, "children": [], "feats": {}, "snt_id": null}, {"form": "by", "prnt": null, "lemma": null, "tag": null, "rel": null, "children": [], "feats": {}, "snt_id": null}, {"form": "an", "prnt": null, "lemma": null, "tag": null, "rel": null, "children": [], "feats": {}, "snt_id": null}, {"form": "arli$$", "prnt": null, "lemma": null, "tag": null, "rel": null, "children": [], "feats": {}, "snt_id": null}, {"form": "writing", "prnt": null, "lemma": null, "tag": null, "rel": null, "children": [], "feats": {}, "snt_id": null}, {"form": "alumnus", "prnt": null, "lemma": null, "tag": null, "rel": null, "children": [], "feats": {}, "snt_id": null}, {"form": "and", "prnt": null, "lemma": null, "tag": null, "rel": null, "children": [], "feats": {}, "snt_id": null}, {"form": "a", "prnt": null, "lemma": null, "tag": null, "rel": null, "children": [], "feats": {}, "snt_id": null}, {"form": "guy", "prnt": null, "lemma": null, "tag": null, "rel": null, "children": [], "feats": {}, "snt_id": null}, {"form": "that", "prnt": null, "lemma": null, "tag": null, "rel": null, "children": [], "feats": {}, "snt_id": null}, {"form": "starred", "prnt": null, "lemma": null, "tag": null, "rel": null, "children": [], "feats": {}, "snt_id": null}, {"form": "in", "prnt": null, "lemma": null, "tag": null, "rel": null, "children": [], "feats": {}, "snt_id": null}, {"form": "leprechaun", "prnt": null, "lemma": null, "tag": null, "rel": null, "children": [], "feats": {}, "snt_id": null}, {"form": "3", "prnt": null, "lemma": null, "tag": null, "rel": null, "children": [], "feats": {}, "snt_id": null}, {"form": ")", "prnt": null, "lemma": null, "tag": null, "rel": null, "children": [], "feats": {}, "snt_id": null}, {"form": ",", "prnt": null, "lemma": null, "tag": null, "rel": null, "children": [], "feats": {}, "snt_id": null}, {"form": "chock-full", "prnt": null, "lemma": null, "tag": null, "rel": null, "children": [], "feats": {}, "snt_id": null}, {"form": "of", "prnt": null, "lemma": null, "tag": null, "rel": null, "children": [], "feats": {}, "snt_id": null}, {"form": "phony", "prnt": null, "lemma": null, "tag": null, "rel": null, "children": [], "feats": {}, "snt_id": null}, {"form": "emotion", "prnt": null, "lemma": null, "tag": null, "rel": null, "children": [], "feats": {}, "snt_id": null}, {"form": ".", "prnt": null, "lemma": null, "tag": null, "rel": null, "children": [], "feats": {}, "snt_id": null}], "edus": [], "rst_trees": {}, "polarity_scores": []}, {"text": "by the end , it all becomes a platform for each character to deliver a soliloquy to ryan that he must take to heart .", "msg_id": "cv643_29282_13", "label": "negative", "toks": [{"form": "by", "prnt": null, "lemma": null, "tag": null, "rel": null, "children": [], "feats": {}, "snt_id": null}, {"form": "the", "prnt": null, "lemma": null, "tag": null, "rel": null, "children": [], "feats": {}, "snt_id": null}, {"form": "end", "prnt": null, "lemma": null, "tag": null, "rel": null, "children": [], "feats": {}, "snt_id": null}, {"form": ",", "prnt": null, "lemma": null, "tag": null, "rel": null, "children": [], "feats": {}, "snt_id": null}, {"form": "it", "prnt": null, "lemma": null, "tag": null, "rel": null, "children": [], "feats": {}, "snt_id": null}, {"form": "all", "prnt": null, "lemma": null, "tag": null, "rel": null, "children": [], "feats": {}, "snt_id": null}, {"form": "becomes", "prnt": null, "lemma": null, "tag": null, "rel": null, "children": [], "feats": {}, "snt_id": null}, {"form": "a", "prnt": null, "lemma": null, "tag": null, "rel": null, "children": [], "feats": {}, "snt_id": null}, {"form": "platform", "prnt": null, "lemma": null, "tag": null, "rel": null, "children": [], "feats": {}, "snt_id": null}, {"form": "for", "prnt": null, "lemma": null, "tag": null, "rel": null, "children": [], "feats": {}, "snt_id": null}, {"form": "each", "prnt": null, "lemma": null, "tag": null, "rel": null, "children": [], "feats": {}, "snt_id": null}, {"form": "character", "prnt": null, "lemma": null, "tag": null, "rel": null, "children": [], "feats": {}, "snt_id": null}, {"form": "to", "prnt": null, "lemma": null, "tag": null, "rel": null, "children": [], "feats": {}, "snt_id": null}, {"form": "deliver", "prnt": null, "lemma": null, "tag": null, "rel": null, "children": [], "feats": {}, "snt_id": null}, {"form": "a", "prnt": null, "lemma": null, "tag": null, "rel": null, "children": [], "feats": {}, "snt_id": null}, {"form": "soliloquy", "prnt": null, "lemma": null, "tag": null, "rel": null, "children": [], "feats": {}, "snt_id": null}, {"form": "to", "prnt": null, "lemma": null, "tag": null, "rel": null, "children": [], "feats": {}, "snt_id": null}, {"form": "ryan", "prnt": null, "lemma": null, "tag": null, "rel": null, "children": [], "feats": {}, "snt_id": null}, {"form": "that", "prnt": null, "lemma": null, "tag": null, "rel": null, "children": [], "feats": {}, "snt_id": null}, {"form": "he", "prnt": null, "lemma": null, "tag": null, "rel": null, "children": [], "feats": {}, "snt_id": null}, {"form": "must", "prnt": null, "lemma": null, "tag": null, "rel": null, "children": [], "feats": {}, "snt_id": null}, {"form": "take", "prnt": null, "lemma": null, "tag": null, "rel": null, "children": [], "feats": {}, "snt_id": null}, {"form": "to", "prnt": null, "lemma": null, "tag": null, "rel": null, "children": [], "feats": {}, "snt_id": null}, {"form": "heart", "prnt": null, "lemma": null, "tag": null, "rel": null, "children": [], "feats": {}, "snt_id": null}, {"form": ".", "prnt": null, "lemma": null, "tag": null, "rel": null, "children": [], "feats": {}, "snt_id": null}], "edus": [], "rst_trees": {}, "polarity_scores": []}, {"text": "dad is on hand to give fatherly yet drunken advice .", "msg_id": "cv643_29282_14", "label": "negative", "toks": [{"form": "dad", "prnt": null, "lemma": null, "tag": null, "rel": null, "children": [], "feats": {}, "snt_id": null}, {"form": "is", "prnt": null, "lemma": null, "tag": null, "rel": null, "children": [], "feats": {}, "snt_id": null}, {"form": "on", "prnt": null, "lemma": null, "tag": null, "rel": null, "children": [], "feats": {}, "snt_id": null}, {"form": "hand", "prnt": null, "lemma": null, "tag": null, "rel": null, "children": [], "feats": {}, "snt_id": null}, {"form": "to", "prnt": null, "lemma": null, "tag": null, "rel": null, "children": [], "feats": {}, "snt_id": null}, {"form": "give", "prnt": null, "lemma": null, "tag": null, "rel": null, "children": [], "feats": {}, "snt_id": null}, {"form": "fatherly", "prnt": null, "lemma": null, "tag": null, "rel": null, "children": [], "feats": {}, "snt_id": null}, {"form": "yet", "prnt": null, "lemma": null, "tag": null, "rel": null, "children": [], "feats": {}, "snt_id": null}, {"form": "drunken", "prnt": null, "lemma": null, "tag": null, "rel": null, "children": [], "feats": {}, "snt_id": null}, {"form": "advice", "prnt": null, "lemma": null, "tag": null, "rel": null, "children": [], "feats": {}, "snt_id": null}, {"form": ".", "prnt": null, "lemma": null, "tag": null, "rel": null, "children": [], "feats": {}, "snt_id": null}], "edus": [], "rst_trees": {}, "polarity_scores": []}, {"text": "coach ( brian dennehy , just loving the fact that he's got some work on the big screen ) is on hand to give the curmudgeonly counterpoint .", "msg_id": "cv643_29282_15", "label": "negative", "toks": [{"form": "coach", "prnt": null, "lemma": null, "tag": null, "rel": null, "children": [], "feats": {}, "snt_id": null}, {"form": "(", "prnt": null, "lemma": null, "tag": null, "rel": null, "children": [], "feats": {}, "snt_id": null}, {"form": "brian", "prnt": null, "lemma": null, "tag": null, "rel": null, "children": [], "feats": {}, "snt_id": null}, {"form": "dennehy", "prnt": null, "lemma": null, "tag": null, "rel": null, "children": [], "feats": {}, "snt_id": null}, {"form": ",", "prnt": null, "lemma": null, "tag": null, "rel": null, "children": [], "feats": {}, "snt_id": null}, {"form": "just", "prnt": null, "lemma": null, "tag": null, "rel": null, "children": [], "feats": {}, "snt_id": null}, {"form": "loving", "prnt": null, "lemma": null, "tag": null, "rel": null, "children": [], "feats": {}, "snt_id": null}, {"form": "the", "prnt": null, "lemma": null, "tag": null, "rel": null, "children": [], "feats": {}, "snt_id": null}, {"form": "fact", "prnt": null, "lemma": null, "tag": null, "rel": null, "children": [], "feats": {}, "snt_id": null}, {"form": "that", "prnt": null, "lemma": null, "tag": null, "rel": null, "children": [], "feats": {}, "snt_id": null}, {"form": "he's", "prnt": null, "lemma": null, "tag": null, "rel": null, "children": [], "feats": {}, "snt_id": null}, {"form": "got", "prnt": null, "lemma": null, "tag": null, "rel": null, "children": [], "feats": {}, "snt_id": null}, {"form": "some", "prnt": null, "lemma": null, "tag": null, "rel": null, "children": [], "feats": {}, "snt_id": null}, {"form": "work", "prnt": null, "lemma": null, "tag": null, "rel": null, "children": [], "feats": {}, "snt_id": null}, {"form": "on", "prnt": null, "lemma": null, "tag": null, "rel": null, "children": [], "feats": {}, "snt_id": null}, {"form": "the", "prnt": null, "lemma": null, "tag": null, "rel": null, "children": [], "feats": {}, "snt_id": null}, {"form": "big", "prnt": null, "lemma": null, "tag": null, "rel": null, "children": [], "feats": {}, "snt_id": null}, {"form": "screen", "prnt": null, "lemma": null, "tag": null, "rel": null, "children": [], "feats": {}, "snt_id": null}, {"form": ")", "prnt": null, "lemma": null, "tag": null, "rel": null, "children": [], "feats": {}, "snt_id": null}, {"form": "is", "prnt": null, "lemma": null, "tag": null, "rel": null, "children": [], "feats": {}, "snt_id": null}, {"form": "on", "prnt": null, "lemma": null, "tag": null, "rel": null, "children": [], "feats": {}, "snt_id": null}, {"form": "hand", "prnt": null, "lemma": null, "tag": null, "rel": null, "children": [], "feats": {}, "snt_id": null}, {"form": "to", "prnt": null, "lemma": null, "tag": null, "rel": null, "children": [], "feats": {}, "snt_id": null}, {"form": "give", "prnt": null, "lemma": null, "tag": null, "rel": null, "children": [], "feats": {}, "snt_id": null}, {"form": "the", "prnt": null, "lemma": null, "tag": null, "rel": null, "children": [], "feats": {}, "snt_id": null}, {"form": "curmudgeonly", "prnt": null, "lemma": null, "tag": null, "rel": null, "children": [], "feats": {}, "snt_id": null}, {"form": "counterpoint", "prnt": null, "lemma": null, "tag": null, "rel": null, "children": [], "feats": {}, "snt_id": null}, {"form": ".", "prnt": null, "lemma": null, "tag": null, "rel": null, "children": [], "feats": {}, "snt_id": null}], "edus": [], "rst_trees": {}, "polarity_scores": []}, {"text": "ryan's catcher ( matthew lillard , playing himself again ) is on hand to tell ryan to \" play catch \" with him and make fun of the fat fetish guy .", "msg_id": "cv643_29282_16", "label": "negative", "toks": [{"form": "ryan's", "prnt": null, "lemma": null, "tag": null, "rel": null, "children": [], "feats": {}, "snt_id": null}, {"form": "catcher", "prnt": null, "lemma": null, "tag": null, "rel": null, "children": [], "feats": {}, "snt_id": null}, {"form": "(", "prnt": null, "lemma": null, "tag": null, "rel": null, "children": [], "feats": {}, "snt_id": null}, {"form": "matthew", "prnt": null, "lemma": null, "tag": null, "rel": null, "children": [], "feats": {}, "snt_id": null}, {"form": "lillard", "prnt": null, "lemma": null, "tag": null, "rel": null, "children": [], "feats": {}, "snt_id": null}, {"form": ",", "prnt": null, "lemma": null, "tag": null, "rel": null, "children": [], "feats": {}, "snt_id": null}, {"form": "playing", "prnt": null, "lemma": null, "tag": null, "rel": null, "children": [], "feats": {}, "snt_id": null}, {"form": "himself", "prnt": null, "lemma": null, "tag": null, "rel": null, "children": [], "feats": {}, "snt_id": null}, {"form": "again", "prnt": null, "lemma": null, "tag": null, "rel": null, "children": [], "feats": {}, "snt_id": null}, {"form": ")", "prnt": null, "lemma": null, "tag": null, "rel": null, "children": [], "feats": {}, "snt_id": null}, {"form": "is", "prnt": null, "lemma": null, "tag": null, "rel": null, "children": [], "feats": {}, "snt_id": null}, {"form": "on", "prnt": null, "lemma": null, "tag": null, "rel": null, "children": [], "feats": {}, "snt_id": null}, {"form": "hand", "prnt": null, "lemma": null, "tag": null, "rel": null, "children": [], "feats": {}, "snt_id": null}, {"form": "to", "prnt": null, "lemma": null, "tag": null, "rel": null, "children": [], "feats": {}, "snt_id": null}, {"form": "tell", "prnt": null, "lemma": null, "tag": null, "rel": null, "children": [], "feats": {}, "snt_id": null}, {"form": "ryan", "prnt": null, "lemma": null, "tag": null, "rel": null, "children": [], "feats": {}, "snt_id": null}, {"form": "to", "prnt": null, "lemma": null, "tag": null, "rel": null, "children": [], "feats": {}, "snt_id": null}, {"form": "\"", "prnt": null, "lemma": null, "tag": null, "rel": null, "children": [], "feats": {}, "snt_id": null}, {"form": "play", "prnt": null, "lemma": null, "tag": null, "rel": null, "children": [], "feats": {}, "snt_id": null}, {"form": "catch", "prnt": null, "lemma": null, "tag": null, "rel": null, "children": [], "feats": {}, "snt_id": null}, {"form": "\"", "prnt": null, "lemma": null, "tag": null, "rel": null, "children": [], "feats": {}, "snt_id": null}, {"form": "with", "prnt": null, "lemma": null, "tag": null, "rel": null, "children": [], "feats": {}, "snt_id": null}, {"form": "him", "prnt": null, "lemma": null, "tag": null, "rel": null, "children": [], "feats": {}, "snt_id": null}, {"form": "and", "prnt": null, "lemma": null, "tag": null, "rel": null, "children": [], "feats": {}, "snt_id": null}, {"form": "make", "prnt": null, "lemma": null, "tag": null, "rel": null, "children": [], "feats": {}, "snt_id": null}, {"form": "fun", "prnt": null, "lemma": null, "tag": null, "rel": null, "children": [], "feats": {}, "snt_id": null}, {"form": "of", "prnt": null, "lemma": null, "tag": null, "rel": null, "children": [], "feats": {}, "snt_id": null}, {"form": "the", "prnt": null, "lemma": null, "tag": null, "rel": null, "children": [], "feats": {}, "snt_id": null}, {"form": "fat", "prnt": null, "lemma": null, "tag": null, "rel": null, "children": [], "feats": {}, "snt_id": null}, {"form": "fetish", "prnt": null, "lemma": null, "tag": null, "rel": null, "children": [], "feats": {}, "snt_id": null}, {"form": "guy", "prnt": null, "lemma": null, "tag": null, "rel": null, "children": [], "feats": {}, "snt_id": null}, {"form": ".", "prnt": null, "lemma": null, "tag": null, "rel": null, "children": [], "feats": {}, "snt_id": null}], "edus": [], "rst_trees": {}, "polarity_scores": []}, {"text": "ryan's stoner best friend is on hand to give the go-get-'em-tiger-we're-behind-you talk .", "msg_id": "cv643_29282_17", "label": "negative", "toks": [{"form": "ryan's", "prnt": null, "lemma": null, "tag": null, "rel": null, "children": [], "feats": {}, "snt_id": null}, {"form": "stoner", "prnt": null, "lemma": null, "tag": null, "rel": null, "children": [], "feats": {}, "snt_id": null}, {"form": "best", "prnt": null, "lemma": null, "tag": null, "rel": null, "children": [], "feats": {}, "snt_id": null}, {"form": "friend", "prnt": null, "lemma": null, "tag": null, "rel": null, "children": [], "feats": {}, "snt_id": null}, {"form": "is", "prnt": null, "lemma": null, "tag": null, "rel": null, "children": [], "feats": {}, "snt_id": null}, {"form": "on", "prnt": null, "lemma": null, "tag": null, "rel": null, "children": [], "feats": {}, "snt_id": null}, {"form": "hand", "prnt": null, "lemma": null, "tag": null, "rel": null, "children": [], "feats": {}, "snt_id": null}, {"form": "to", "prnt": null, "lemma": null, "tag": null, "rel": null, "children": [], "feats": {}, "snt_id": null}, {"form": "give", "prnt": null, "lemma": null, "tag": null, "rel": null, "children": [], "feats": {}, "snt_id": null}, {"form": "the", "prnt": null, "lemma": null, "tag": null, "rel": null, "children": [], "feats": {}, "snt_id": null}, {"form": "go-get-'em-tiger-we're-behind-you", "prnt": null, "lemma": null, "tag": null, "rel": null, "children": [], "feats": {}, "snt_id": null}, {"form": "talk", "prnt": null, "lemma": null, "tag": null, "rel": null, "children": [], "feats": {}, "snt_id": null}, {"form": ".", "prnt": null, "lemma": null, "tag": null, "rel": null, "children": [], "feats": {}, "snt_id": null}], "edus": [], "rst_trees": {}, "polarity_scores": []}, {"text": "and the girlfriend is on hand to give heartwarming-nuzzly-follow-your-dreams counsel .", "msg_id": "cv643_29282_18", "label": "negative", "toks": [{"form": "and", "prnt": null, "lemma": null, "tag": null, "rel": null, "children": [], "feats": {}, "snt_id": null}, {"form": "the", "prnt": null, "lemma": null, "tag": null, "rel": null, "children": [], "feats": {}, "snt_id": null}, {"form": "girlfriend", "prnt": null, "lemma": null, "tag": null, "rel": null, "children": [], "feats": {}, "snt_id": null}, {"form": "is", "prnt": null, "lemma": null, "tag": null, "rel": null, "children": [], "feats": {}, "snt_id": null}, {"form": "on", "prnt": null, "lemma": null, "tag": null, "rel": null, "children": [], "feats": {}, "snt_id": null}, {"form": "hand", "prnt": null, "lemma": null, "tag": null, "rel": null, "children": [], "feats": {}, "snt_id": null}, {"form": "to", "prnt": null, "lemma": null, "tag": null, "rel": null, "children": [], "feats": {}, "snt_id": null}, {"form": "give", "prnt": null, "lemma": null, "tag": null, "rel": null, "children": [], "feats": {}, "snt_id": null}, {"form": "heartwarming-nuzzly-follow-your-dreams", "prnt": null, "lemma": null, "tag": null, "rel": null, "children": [], "feats": {}, "snt_id": null}, {"form": "counsel", "prnt": null, "lemma": null, "tag": null, "rel": null, "children": [], "feats": {}, "snt_id": null}, {"form": ".", "prnt": null, "lemma": null, "tag": null, "rel": null, "children": [], "feats": {}, "snt_id": null}], "edus": [], "rst_trees": {}, "polarity_scores": []}, {"text": "before long , you start to wonder : is freddy prinze jr . is capable of having a thought of his own ?", "msg_id": "cv643_29282_19", "label": "negative", "toks": [{"form": "before", "prnt": null, "lemma": null, "tag": null, "rel": null, "children": [], "feats": {}, "snt_id": null}, {"form": "long", "prnt": null, "lemma": null, "tag": null, "rel": null, "children": [], "feats": {}, "snt_id": null}, {"form": ",", "prnt": null, "lemma": null, "tag": null, "rel": null, "children": [], "feats": {}, "snt_id": null}, {"form": "you", "prnt": null, "lemma": null, "tag": null, "rel": null, "children": [], "feats": {}, "snt_id": null}, {"form": "start", "prnt": null, "lemma": null, "tag": null, "rel": null, "children": [], "feats": {}, "snt_id": null}, {"form": "to", "prnt": null, "lemma": null, "tag": null, "rel": null, "children": [], "feats": {}, "snt_id": null}, {"form": "wonder", "prnt": null, "lemma": null, "tag": null, "rel": null, "children": [], "feats": {}, "snt_id": null}, {"form": ":", "prnt": null, "lemma": null, "tag": null, "rel": null, "children": [], "feats": {}, "snt_id": null}, {"form": "is", "prnt": null, "lemma": null, "tag": null, "rel": null, "children": [], "feats": {}, "snt_id": null}, {"form": "freddy", "prnt": null, "lemma": null, "tag": null, "rel": null, "children": [], "feats": {}, "snt_id": null}, {"form": "prinze", "prnt": null, "lemma": null, "tag": null, "rel": null, "children": [], "feats": {}, "snt_id": null}, {"form": "jr", "prnt": null, "lemma": null, "tag": null, "rel": null, "children": [], "feats": {}, "snt_id": null}, {"form": ".", "prnt": null, "lemma": null, "tag": null, "rel": null, "children": [], "feats": {}, "snt_id": null}, {"form": "is", "prnt": null, "lemma": null, "tag": null, "rel": null, "children": [], "feats": {}, "snt_id": null}, {"form": "capable", "prnt": null, "lemma": null, "tag": null, "rel": null, "children": [], "feats": {}, "snt_id": null}, {"form": "of", "prnt": null, "lemma": null, "tag": null, "rel": null, "children": [], "feats": {}, "snt_id": null}, {"form": "having", "prnt": null, "lemma": null, "tag": null, "rel": null, "children": [], "feats": {}, "snt_id": null}, {"form": "a", "prnt": null, "lemma": null, "tag": null, "rel": null, "children": [], "feats": {}, "snt_id": null}, {"form": "thought", "prnt": null, "lemma": null, "tag": null, "rel": null, "children": [], "feats": {}, "snt_id": null}, {"form": "of", "prnt": null, "lemma": null, "tag": null, "rel": null, "children": [], "feats": {}, "snt_id": null}, {"form": "his", "prnt": null, "lemma": null, "tag": null, "rel": null, "children": [], "feats": {}, "snt_id": null}, {"form": "own", "prnt": null, "lemma": null, "tag": null, "rel": null, "children": [], "feats": {}, "snt_id": null}, {"form": "?", "prnt": null, "lemma": null, "tag": null, "rel": null, "children": [], "feats": {}, "snt_id": null}], "edus": [], "rst_trees": {}, "polarity_scores": []}, {"text": "don't answer that .", "msg_id": "cv643_29282_20", "label": "negative", "toks": [{"form": "don't", "prnt": null, "lemma": null, "tag": null, "rel": null, "children": [], "feats": {}, "snt_id": null}, {"form": "answer", "prnt": null, "lemma": null, "tag": null, "rel": null, "children": [], "feats": {}, "snt_id": null}, {"form": "that", "prnt": null, "lemma": null, "tag": null, "rel": null, "children": [], "feats": {}, "snt_id": null}, {"form": ".", "prnt": null, "lemma": null, "tag": null, "rel": null, "children": [], "feats": {}, "snt_id": null}], "edus": [], "rst_trees": {}, "polarity_scores": []}, {"text": "the only real joy in the film is found in biel's character , and not just because of the skimpy outfits , which are also usually wet .", "msg_id": "cv643_29282_21", "label": "negative", "toks": [{"form": "the", "prnt": null, "lemma": null, "tag": null, "rel": null, "children": [], "feats": {}, "snt_id": null}, {"form": "only", "prnt": null, "lemma": null, "tag": null, "rel": null, "children": [], "feats": {}, "snt_id": null}, {"form": "real", "prnt": null, "lemma": null, "tag": null, "rel": null, "children": [], "feats": {}, "snt_id": null}, {"form": "joy", "prnt": null, "lemma": null, "tag": null, "rel": null, "children": [], "feats": {}, "snt_id": null}, {"form": "in", "prnt": null, "lemma": null, "tag": null, "rel": null, "children": [], "feats": {}, "snt_id": null}, {"form": "the", "prnt": null, "lemma": null, "tag": null, "rel": null, "children": [], "feats": {}, "snt_id": null}, {"form": "film", "prnt": null, "lemma": null, "tag": null, "rel": null, "children": [], "feats": {}, "snt_id": null}, {"form": "is", "prnt": null, "lemma": null, "tag": null, "rel": null, "children": [], "feats": {}, "snt_id": null}, {"form": "found", "prnt": null, "lemma": null, "tag": null, "rel": null, "children": [], "feats": {}, "snt_id": null}, {"form": "in", "prnt": null, "lemma": null, "tag": null, "rel": null, "children": [], "feats": {}, "snt_id": null}, {"form": "biel's", "prnt": null, "lemma": null, "tag": null, "rel": null, "children": [], "feats": {}, "snt_id": null}, {"form": "character", "prnt": null, "lemma": null, "tag": null, "rel": null, "children": [], "feats": {}, "snt_id": null}, {"form": ",", "prnt": null, "lemma": null, "tag": null, "rel": null, "children": [], "feats": {}, "snt_id": null}, {"form": "and", "prnt": null, "lemma": null, "tag": null, "rel": null, "children": [], "feats": {}, "snt_id": null}, {"form": "not", "prnt": null, "lemma": null, "tag": null, "rel": null, "children": [], "feats": {}, "snt_id": null}, {"form": "just", "prnt": null, "lemma": null, "tag": null, "rel": null, "children": [], "feats": {}, "snt_id": null}, {"form": "because", "prnt": null, "lemma": null, "tag": null, "rel": null, "children": [], "feats": {}, "snt_id": null}, {"form": "of", "prnt": null, "lemma": null, "tag": null, "rel": null, "children": [], "feats": {}, "snt_id": null}, {"form": "the", "prnt": null, "lemma": null, "tag": null, "rel": null, "children": [], "feats": {}, "snt_id": null}, {"form": "skimpy", "prnt": null, "lemma": null, "tag": null, "rel": null, "children": [], "feats": {}, "snt_id": null}, {"form": "outfits", "prnt": null, "lemma": null, "tag": null, "rel": null, "children": [], "feats": {}, "snt_id": null}, {"form": ",", "prnt": null, "lemma": null, "tag": null, "rel": null, "children": [], "feats": {}, "snt_id": null}, {"form": "which", "prnt": null, "lemma": null, "tag": null, "rel": null, "children": [], "feats": {}, "snt_id": null}, {"form": "are", "prnt": null, "lemma": null, "tag": null, "rel": null, "children": [], "feats": {}, "snt_id": null}, {"form": "also", "prnt": null, "lemma": null, "tag": null, "rel": null, "children": [], "feats": {}, "snt_id": null}, {"form": "usually", "prnt": null, "lemma": null, "tag": null, "rel": null, "children": [], "feats": {}, "snt_id": null}, {"form": "wet", "prnt": null, "lemma": null, "tag": null, "rel": null, "children": [], "feats": {}, "snt_id": null}, {"form": ".", "prnt": null, "lemma": null, "tag": null, "rel": null, "children": [], "feats": {}, "snt_id": null}], "edus": [], "rst_trees": {}, "polarity_scores": []}, {"text": "she's the only one in the movie that is able to do much with her role , taking the rebelling-against-daddy character to at least a passing grade .", "msg_id": "cv643_29282_22", "label": "negative", "toks": [{"form": "she's", "prnt": null, "lemma": null, "tag": null, "rel": null, "children": [], "feats": {}, "snt_id": null}, {"form": "the", "prnt": null, "lemma": null, "tag": null, "rel": null, "children": [], "feats": {}, "snt_id": null}, {"form": "only", "prnt": null, "lemma": null, "tag": null, "rel": null, "children": [], "feats": {}, "snt_id": null}, {"form": "one", "prnt": null, "lemma": null, "tag": null, "rel": null, "children": [], "feats": {}, "snt_id": null}, {"form": "in", "prnt": null, "lemma": null, "tag": null, "rel": null, "children": [], "feats": {}, "snt_id": null}, {"form": "the", "prnt": null, "lemma": null, "tag": null, "rel": null, "children": [], "feats": {}, "snt_id": null}, {"form": "movie", "prnt": null, "lemma": null, "tag": null, "rel": null, "children": [], "feats": {}, "snt_id": null}, {"form": "that", "prnt": null, "lemma": null, "tag": null, "rel": null, "children": [], "feats": {}, "snt_id": null}, {"form": "is", "prnt": null, "lemma": null, "tag": null, "rel": null, "children": [], "feats": {}, "snt_id": null}, {"form": "able", "prnt": null, "lemma": null, "tag": null, "rel": null, "children": [], "feats": {}, "snt_id": null}, {"form": "to", "prnt": null, "lemma": null, "tag": null, "rel": null, "children": [], "feats": {}, "snt_id": null}, {"form": "do", "prnt": null, "lemma": null, "tag": null, "rel": null, "children": [], "feats": {}, "snt_id": null}, {"form": "much", "prnt": null, "lemma": null, "tag": null, "rel": null, "children": [], "feats": {}, "snt_id": null}, {"form": "with", "prnt": null, "lemma": null, "tag": null, "rel": null, "children": [], "feats": {}, "snt_id": null}, {"form": "her", "prnt": null, "lemma": null, "tag": null, "rel": null, "children": [], "feats": {}, "snt_id": null}, {"form": "role", "prnt": null, "lemma": null, "tag": null, "rel": null, "children": [], "feats": {}, "snt_id": null}, {"form": ",", "prnt": null, "lemma": null, "tag": null, "rel": null, "children": [], "feats": {}, "snt_id": null}, {"form": "taking", "prnt": null, "lemma": null, "tag": null, "rel": null, "children": [], "feats": {}, "snt_id": null}, {"form": "the", "prnt": null, "lemma": null, "tag": null, "rel": null, "children": [], "feats": {}, "snt_id": null}, {"form": "rebelling-against-daddy", "prnt": null, "lemma": null, "tag": null, "rel": null, "children": [], "feats": {}, "snt_id": null}, {"form": "character", "prnt": null, "lemma": null, "tag": null, "rel": null, "children": [], "feats": {}, "snt_id": null}, {"form": "to", "prnt": null, "lemma": null, "tag": null, "rel": null, "children": [], "feats": {}, "snt_id": null}, {"form": "at", "prnt": null, "lemma": null, "tag": null, "rel": null, "children": [], "feats": {}, "snt_id": null}, {"form": "least", "prnt": null, "lemma": null, "tag": null, "rel": null, "children": [], "feats": {}, "snt_id": null}, {"form": "a", "prnt": null, "lemma": null, "tag": null, "rel": null, "children": [], "feats": {}, "snt_id": null}, {"form": "passing", "prnt": null, "lemma": null, "tag": null, "rel": null, "children": [], "feats": {}, "snt_id": null}, {"form": "grade", "prnt": null, "lemma": null, "tag": null, "rel": null, "children": [], "feats": {}, "snt_id": null}, {"form": ".", "prnt": null, "lemma": null, "tag": null, "rel": null, "children": [], "feats": {}, "snt_id": null}], "edus": [], "rst_trees": {}, "polarity_scores": []}, {"text": "when she's on screen , the time flies by .", "msg_id": "cv643_29282_23", "label": "negative", "toks": [{"form": "when", "prnt": null, "lemma": null, "tag": null, "rel": null, "children": [], "feats": {}, "snt_id": null}, {"form": "she's", "prnt": null, "lemma": null, "tag": null, "rel": null, "children": [], "feats": {}, "snt_id": null}, {"form": "on", "prnt": null, "lemma": null, "tag": null, "rel": null, "children": [], "feats": {}, "snt_id": null}, {"form": "screen", "prnt": null, "lemma": null, "tag": null, "rel": null, "children": [], "feats": {}, "snt_id": null}, {"form": ",", "prnt": null, "lemma": null, "tag": null, "rel": null, "children": [], "feats": {}, "snt_id": null}, {"form": "the", "prnt": null, "lemma": null, "tag": null, "rel": null, "children": [], "feats": {}, "snt_id": null}, {"form": "time", "prnt": null, "lemma": null, "tag": null, "rel": null, "children": [], "feats": {}, "snt_id": null}, {"form": "flies", "prnt": null, "lemma": null, "tag": null, "rel": null, "children": [], "feats": {}, "snt_id": null}, {"form": "by", "prnt": null, "lemma": null, "tag": null, "rel": null, "children": [], "feats": {}, "snt_id": null}, {"form": ".", "prnt": null, "lemma": null, "tag": null, "rel": null, "children": [], "feats": {}, "snt_id": null}], "edus": [], "rst_trees": {}, "polarity_scores": []}, {"text": "when she's not , you realize that for some ungodly reason this movie is almost two hours long .", "msg_id": "cv643_29282_24", "label": "negative", "toks": [{"form": "when", "prnt": null, "lemma": null, "tag": null, "rel": null, "children": [], "feats": {}, "snt_id": null}, {"form": "she's", "prnt": null, "lemma": null, "tag": null, "rel": null, "children": [], "feats": {}, "snt_id": null}, {"form": "not", "prnt": null, "lemma": null, "tag": null, "rel": null, "children": [], "feats": {}, "snt_id": null}, {"form": ",", "prnt": null, "lemma": null, "tag": null, "rel": null, "children": [], "feats": {}, "snt_id": null}, {"form": "you", "prnt": null, "lemma": null, "tag": null, "rel": null, "children": [], "feats": {}, "snt_id": null}, {"form": "realize", "prnt": null, "lemma": null, "tag": null, "rel": null, "children": [], "feats": {}, "snt_id": null}, {"form": "that", "prnt": null, "lemma": null, "tag": null, "rel": null, "children": [], "feats": {}, "snt_id": null}, {"form": "for", "prnt": null, "lemma": null, "tag": null, "rel": null, "children": [], "feats": {}, "snt_id": null}, {"form": "some", "prnt": null, "lemma": null, "tag": null, "rel": null, "children": [], "feats": {}, "snt_id": null}, {"form": "ungodly", "prnt": null, "lemma": null, "tag": null, "rel": null, "children": [], "feats": {}, "snt_id": null}, {"form": "reason", "prnt": null, "lemma": null, "tag": null, "rel": null, "children": [], "feats": {}, "snt_id": null}, {"form": "this", "prnt": null, "lemma": null, "tag": null, "rel": null, "children": [], "feats": {}, "snt_id": null}, {"form": "movie", "prnt": null, "lemma": null, "tag": null, "rel": null, "children": [], "feats": {}, "snt_id": null}, {"form": "is", "prnt": null, "lemma": null, "tag": null, "rel": null, "children": [], "feats": {}, "snt_id": null}, {"form": "almost", "prnt": null, "lemma": null, "tag": null, "rel": null, "children": [], "feats": {}, "snt_id": null}, {"form": "two", "prnt": null, "lemma": null, "tag": null, "rel": null, "children": [], "feats": {}, "snt_id": null}, {"form": "hours", "prnt": null, "lemma": null, "tag": null, "rel": null, "children": [], "feats": {}, "snt_id": null}, {"form": "long", "prnt": null, "lemma": null, "tag": null, "rel": null, "children": [], "feats": {}, "snt_id": null}, {"form": ".", "prnt": null, "lemma": null, "tag": null, "rel": null, "children": [], "feats": {}, "snt_id": null}], "edus": [], "rst_trees": {}, "polarity_scores": []}, {"text": "for a pg-13 teen romance ( despite near-constant sexual innuendo ) , one has to ask warner brothers : what were you thinking ? ? ?", "msg_id": "cv643_29282_25", "label": "negative", "toks": [{"form": "for", "prnt": null, "lemma": null, "tag": null, "rel": null, "children": [], "feats": {}, "snt_id": null}, {"form": "a", "prnt": null, "lemma": null, "tag": null, "rel": null, "children": [], "feats": {}, "snt_id": null}, {"form": "pg-13", "prnt": null, "lemma": null, "tag": null, "rel": null, "children": [], "feats": {}, "snt_id": null}, {"form": "teen", "prnt": null, "lemma": null, "tag": null, "rel": null, "children": [], "feats": {}, "snt_id": null}, {"form": "romance", "prnt": null, "lemma": null, "tag": null, "rel": null, "children": [], "feats": {}, "snt_id": null}, {"form": "(", "prnt": null, "lemma": null, "tag": null, "rel": null, "children": [], "feats": {}, "snt_id": null}, {"form": "despite", "prnt": null, "lemma": null, "tag": null, "rel": null, "children": [], "feats": {}, "snt_id": null}, {"form": "near-constant", "prnt": null, "lemma": null, "tag": null, "rel": null, "children": [], "feats": {}, "snt_id": null}, {"form": "sexual", "prnt": null, "lemma": null, "tag": null, "rel": null, "children": [], "feats": {}, "snt_id": null}, {"form": "innuendo", "prnt": null, "lemma": null, "tag": null, "rel": null, "children": [], "feats": {}, "snt_id": null}, {"form": ")", "prnt": null, "lemma": null, "tag": null, "rel": null, "children": [], "feats": {}, "snt_id": null}, {"form": ",", "prnt": null, "lemma": null, "tag": null, "rel": null, "children": [], "feats": {}, "snt_id": null}, {"form": "one", "prnt": null, "lemma": null, "tag": null, "rel": null, "children": [], "feats": {}, "snt_id": null}, {"form": "has", "prnt": null, "lemma": null, "tag": null, "rel": null, "children": [], "feats": {}, "snt_id": null}, {"form": "to", "prnt": null, "lemma": null, "tag": null, "rel": null, "children": [], "feats": {}, "snt_id": null}, {"form": "ask", "prnt": null, "lemma": null, "tag": null, "rel": null, "children": [], "feats": {}, "snt_id": null}, {"form": "warner", "prnt": null, "lemma": null, "tag": null, "rel": null, "children": [], "feats": {}, "snt_id": null}, {"form": "brothers", "prnt": null, "lemma": null, "tag": null, "rel": null, "children": [], "feats": {}, "snt_id": null}, {"form": ":", "prnt": null, "lemma": null, "tag": null, "rel": null, "children": [], "feats": {}, "snt_id": null}, {"form": "what", "prnt": null, "lemma": null, "tag": null, "rel": null, "children": [], "feats": {}, "snt_id": null}, {"form": "were", "prnt": null, "lemma": null, "tag": null, "rel": null, "children": [], "feats": {}, "snt_id": null}, {"form": "you", "prnt": null, "lemma": null, "tag": null, "rel": null, "children": [], "feats": {}, "snt_id": null}, {"form": "thinking", "prnt": null, "lemma": null, "tag": null, "rel": null, "children": [], "feats": {}, "snt_id": null}, {"form": "?", "prnt": null, "lemma": null, "tag": null, "rel": null, "children": [], "feats": {}, "snt_id": null}, {"form": "?", "prnt": null, "lemma": null, "tag": null, "rel": null, "children": [], "feats": {}, "snt_id": null}, {"form": "?", "prnt": null, "lemma": null, "tag": null, "rel": null, "children": [], "feats": {}, "snt_id": null}], "edus": [], "rst_trees": {}, "polarity_scores": []}, {"text": "for her part , biel has fallen so far from her 7th heaven roots that she has almost become denise richards .", "msg_id": "cv643_29282_26", "label": "negative", "toks": [{"form": "for", "prnt": null, "lemma": null, "tag": null, "rel": null, "children": [], "feats": {}, "snt_id": null}, {"form": "her", "prnt": null, "lemma": null, "tag": null, "rel": null, "children": [], "feats": {}, "snt_id": null}, {"form": "part", "prnt": null, "lemma": null, "tag": null, "rel": null, "children": [], "feats": {}, "snt_id": null}, {"form": ",", "prnt": null, "lemma": null, "tag": null, "rel": null, "children": [], "feats": {}, "snt_id": null}, {"form": "biel", "prnt": null, "lemma": null, "tag": null, "rel": null, "children": [], "feats": {}, "snt_id": null}, {"form": "has", "prnt": null, "lemma": null, "tag": null, "rel": null, "children": [], "feats": {}, "snt_id": null}, {"form": "fallen", "prnt": null, "lemma": null, "tag": null, "rel": null, "children": [], "feats": {}, "snt_id": null}, {"form": "so", "prnt": null, "lemma": null, "tag": null, "rel": null, "children": [], "feats": {}, "snt_id": null}, {"form": "far", "prnt": null, "lemma": null, "tag": null, "rel": null, "children": [], "feats": {}, "snt_id": null}, {"form": "from", "prnt": null, "lemma": null, "tag": null, "rel": null, "children": [], "feats": {}, "snt_id": null}, {"form": "her", "prnt": null, "lemma": null, "tag": null, "rel": null, "children": [], "feats": {}, "snt_id": null}, {"form": "7th", "prnt": null, "lemma": null, "tag": null, "rel": null, "children": [], "feats": {}, "snt_id": null}, {"form": "heaven", "prnt": null, "lemma": null, "tag": null, "rel": null, "children": [], "feats": {}, "snt_id": null}, {"form": "roots", "prnt": null, "lemma": null, "tag": null, "rel": null, "children": [], "feats": {}, "snt_id": null}, {"form": "that", "prnt": null, "lemma": null, "tag": null, "rel": null, "children": [], "feats": {}, "snt_id": null}, {"form": "she", "prnt": null, "lemma": null, "tag": null, "rel": null, "children": [], "feats": {}, "snt_id": null}, {"form": "has", "prnt": null, "lemma": null, "tag": null, "rel": null, "children": [], "feats": {}, "snt_id": null}, {"form": "almost", "prnt": null, "lemma": null, "tag": null, "rel": null, "children": [], "feats": {}, "snt_id": null}, {"form": "become", "prnt": null, "lemma": null, "tag": null, "rel": null, "children": [], "feats": {}, "snt_id": null}, {"form": "denise", "prnt": null, "lemma": null, "tag": null, "rel": null, "children": [], "feats": {}, "snt_id": null}, {"form": "richards", "prnt": null, "lemma": null, "tag": null, "rel": null, "children": [], "feats": {}, "snt_id": null}, {"form": ".", "prnt": null, "lemma": null, "tag": null, "rel": null, "children": [], "feats": {}, "snt_id": null}], "edus": [], "rst_trees": {}, "polarity_scores": []}, {"text": "hollywood is either about to eat her alive . . .", "msg_id": "cv643_29282_27", "label": "negative", "toks": [{"form": "hollywood", "prnt": null, "lemma": null, "tag": null, "rel": null, "children": [], "feats": {}, "snt_id": null}, {"form": "is", "prnt": null, "lemma": null, "tag": null, "rel": null, "children": [], "feats": {}, "snt_id": null}, {"form": "either", "prnt": null, "lemma": null, "tag": null, "rel": null, "children": [], "feats": {}, "snt_id": null}, {"form": "about", "prnt": null, "lemma": null, "tag": null, "rel": null, "children": [], "feats": {}, "snt_id": null}, {"form": "to", "prnt": null, "lemma": null, "tag": null, "rel": null, "children": [], "feats": {}, "snt_id": null}, {"form": "eat", "prnt": null, "lemma": null, "tag": null, "rel": null, "children": [], "feats": {}, "snt_id": null}, {"form": "her", "prnt": null, "lemma": null, "tag": null, "rel": null, "children": [], "feats": {}, "snt_id": null}, {"form": "alive", "prnt": null, "lemma": null, "tag": null, "rel": null, "children": [], "feats": {}, "snt_id": null}, {"form": ".", "prnt": null, "lemma": null, "tag": null, "rel": null, "children": [], "feats": {}, "snt_id": null}, {"form": ".", "prnt": null, "lemma": null, "tag": null, "rel": null, "children": [], "feats": {}, "snt_id": null}, {"form": ".", "prnt": null, "lemma": null, "tag": null, "rel": null, "children": [], "feats": {}, "snt_id": null}], "edus": [], "rst_trees": {}, "polarity_scores": []}, {"text": "or vice versa .", "msg_id": "cv643_29282_28", "label": "negative", "toks": [{"form": "or", "prnt": null, "lemma": null, "tag": null, "rel": null, "children": [], "feats": {}, "snt_id": null}, {"form": "vice", "prnt": null, "lemma": null, "tag": null, "rel": null, "children": [], "feats": {}, "snt_id": null}, {"form": "versa", "prnt": null, "lemma": null, "tag": null, "rel": null, "children": [], "feats": {}, "snt_id": null}, {"form": ".", "prnt": null, "lemma": null, "tag": null, "rel": null, "children": [], "feats": {}, "snt_id": null}], "edus": [], "rst_trees": {}, "polarity_scores": []}, {"text": "either way , good luck , jessica .", "msg_id": "cv643_29282_29", "label": "negative", "toks": [{"form": "either", "prnt": null, "lemma": null, "tag": null, "rel": null, "children": [], "feats": {}, "snt_id": null}, {"form": "way", "prnt": null, "lemma": null, "tag": null, "rel": null, "children": [], "feats": {}, "snt_id": null}, {"form": ",", "prnt": null, "lemma": null, "tag": null, "rel": null, "children": [], "feats": {}, "snt_id": null}, {"form": "good", "prnt": null, "lemma": null, "tag": null, "rel": null, "children": [], "feats": {}, "snt_id": null}, {"form": "luck", "prnt": null, "lemma": null, "tag": null, "rel": null, "children": [], "feats": {}, "snt_id": null}, {"form": ",", "prnt": null, "lemma": null, "tag": null, "rel": null, "children": [], "feats": {}, "snt_id": null}, {"form": "jessica", "prnt": null, "lemma": null, "tag": null, "rel": null, "children": [], "feats": {}, "snt_id": null}, {"form": ".", "prnt": null, "lemma": null, "tag": null, "rel": null, "children": [], "feats": {}, "snt_id": null}], "edus": [], "rst_trees": {}, "polarity_scores": []}, {"text": "as for freddie , if he keeps pumping teen romances out at the rate of two a year , prinze's next \" summer catch \" is liable to be a venereal disease .", "msg_id": "cv643_29282_30", "label": "negative", "toks": [{"form": "as", "prnt": null, "lemma": null, "tag": null, "rel": null, "children": [], "feats": {}, "snt_id": null}, {"form": "for", "prnt": null, "lemma": null, "tag": null, "rel": null, "children": [], "feats": {}, "snt_id": null}, {"form": "freddie", "prnt": null, "lemma": null, "tag": null, "rel": null, "children": [], "feats": {}, "snt_id": null}, {"form": ",", "prnt": null, "lemma": null, "tag": null, "rel": null, "children": [], "feats": {}, "snt_id": null}, {"form": "if", "prnt": null, "lemma": null, "tag": null, "rel": null, "children": [], "feats": {}, "snt_id": null}, {"form": "he", "prnt": null, "lemma": null, "tag": null, "rel": null, "children": [], "feats": {}, "snt_id": null}, {"form": "keeps", "prnt": null, "lemma": null, "tag": null, "rel": null, "children": [], "feats": {}, "snt_id": null}, {"form": "pumping", "prnt": null, "lemma": null, "tag": null, "rel": null, "children": [], "feats": {}, "snt_id": null}, {"form": "teen", "prnt": null, "lemma": null, "tag": null, "rel": null, "children": [], "feats": {}, "snt_id": null}, {"form": "romances", "prnt": null, "lemma": null, "tag": null, "rel": null, "children": [], "feats": {}, "snt_id": null}, {"form": "out", "prnt": null, "lemma": null, "tag": null, "rel": null, "children": [], "feats": {}, "snt_id": null}, {"form": "at", "prnt": null, "lemma": null, "tag": null, "rel": null, "children": [], "feats": {}, "snt_id": null}, {"form": "the", "prnt": null, "lemma": null, "tag": null, "rel": null, "children": [], "feats": {}, "snt_id": null}, {"form": "rate", "prnt": null, "lemma": null, "tag": null, "rel": null, "children": [], "feats": {}, "snt_id": null}, {"form": "of", "prnt": null, "lemma": null, "tag": null, "rel": null, "children": [], "feats": {}, "snt_id": null}, {"form": "two", "prnt": null, "lemma": null, "tag": null, "rel": null, "children": [], "feats": {}, "snt_id": null}, {"form": "a", "prnt": null, "lemma": null, "tag": null, "rel": null, "children": [], "feats": {}, "snt_id": null}, {"form": "year", "prnt": null, "lemma": null, "tag": null, "rel": null, "children": [], "feats": {}, "snt_id": null}, {"form": ",", "prnt": null, "lemma": null, "tag": null, "rel": null, "children": [], "feats": {}, "snt_id": null}, {"form": "prinze's", "prnt": null, "lemma": null, "tag": null, "rel": null, "children": [], "feats": {}, "snt_id": null}, {"form": "next", "prnt": null, "lemma": null, "tag": null, "rel": null, "children": [], "feats": {}, "snt_id": null}, {"form": "\"", "prnt": null, "lemma": null, "tag": null, "rel": null, "children": [], "feats": {}, "snt_id": null}, {"form": "summer", "prnt": null, "lemma": null, "tag": null, "rel": null, "children": [], "feats": {}, "snt_id": null}, {"form": "catch", "prnt": null, "lemma": null, "tag": null, "rel": null, "children": [], "feats": {}, "snt_id": null}, {"form": "\"", "prnt": null, "lemma": null, "tag": null, "rel": null, "children": [], "feats": {}, "snt_id": null}, {"form": "is", "prnt": null, "lemma": null, "tag": null, "rel": null, "children": [], "feats": {}, "snt_id": null}, {"form": "liable", "prnt": null, "lemma": null, "tag": null, "rel": null, "children": [], "feats": {}, "snt_id": null}, {"form": "to", "prnt": null, "lemma": null, "tag": null, "rel": null, "children": [], "feats": {}, "snt_id": null}, {"form": "be", "prnt": null, "lemma": null, "tag": null, "rel": null, "children": [], "feats": {}, "snt_id": null}, {"form": "a", "prnt": null, "lemma": null, "tag": null, "rel": null, "children": [], "feats": {}, "snt_id": null}, {"form": "venereal", "prnt": null, "lemma": null, "tag": null, "rel": null, "children": [], "feats": {}, "snt_id": null}, {"form": "disease", "prnt": null, "lemma": null, "tag": null, "rel": null, "children": [], "feats": {}, "snt_id": null}, {"form": ".", "prnt": null, "lemma": null, "tag": null, "rel": null, "children": [], "feats": {}, "snt_id": null}], "edus": [], "rst_trees": {}, "polarity_scores": []}]}